{
  "0x03d3ce84279cb6f54f5e6074ff0f8319d830dafe": [
    {
      "user": "0xf61397e4b0ff46e78b34d5f72b49b4d46e8c96dd",
      "prizes": {
        "3": [
          15
        ],
        "4": [
          76,
          82
        ],
        "5": [
          645
        ]
      }
    },
    {
      "user": "0xe2d31a02163d2a49aebd19aefcd43b9119700fcf",
      "prizes": {
        "4": [
          126
        ]
      }
    },
    {
      "user": "0x22040d869370ef386d2b52497ead9316947c6062",
      "prizes": {
        "4": [
          155
        ],
        "5": [
          123,
          626,
          771,
          793,
          835
        ]
      }
    },
    {
      "user": "0x174976a7bae6bf9abb80a7bd6896a78fbd17386d",
      "prizes": {
        "4": [
          22,
          51,
          59,
          137,
          140,
          204,
          247
        ],
        "5": [
          49,
          67,
          211,
          215,
          309,
          366,
          381,
          491,
          529,
          618,
          662,
          700,
          732,
          771,
          885,
          912,
          939,
          1014,
          1015
        ]
      }
    },
    {
      "user": "0x1035777a4fab2980d20248d1e4303321d139b021",
      "prizes": {
        "4": [
          94
        ],
        "5": [
          169,
          318,
          329,
          903
        ]
      }
    },
    {
      "user": "0xd9e1bf544ae98c663e108b6c9e0037fd96055b5f",
      "prizes": {
        "4": [
          0,
          93,
          233
        ],
        "5": [
          360,
          371,
          376,
          694,
          736,
          844,
          912
        ]
      }
    },
    {
      "user": "0x6622ba5b4fec399b88d4bdcab09936491ea3781a",
      "prizes": {
        "4": [
          38,
          46,
          49,
          173,
          246
        ],
        "5": [
          11,
          35,
          126,
          135,
          306,
          398,
          412,
          498,
          542,
          581,
          591,
          625,
          822,
          883,
          1003
        ]
      }
    },
    {
      "user": "0x280e4df73c589623eed589d94193a56dab46ba42",
      "prizes": {
        "4": [
          252
        ],
        "5": [
          0
        ]
      }
    },
    {
      "user": "0xc80fdaccc65dcd6ed030fc416190f1c2ab7b12ac",
      "prizes": {
        "4": [
          113
        ],
        "5": [
          590,
          793
        ]
      }
    },
    {
      "user": "0x68a58ef1a05096fa164043d88004d2002f1b89c0",
      "prizes": {
        "4": [
          140
        ],
        "5": [
          554,
          1020
        ]
      }
    },
    {
      "user": "0xab5309888c39646bb222a70e0bc1c69e3326ee77",
      "prizes": {
        "4": [
          139
        ]
      }
    },
    {
      "user": "0x5ffece226e931a43fd2952f03b34c7645159129f",
      "prizes": {
        "4": [
          240
        ]
      }
    },
    {
      "user": "0xb367782bbc3376dae3b89669cc89c9de200e70e2",
      "prizes": {
        "4": [
          136
        ],
        "5": [
          54,
          525
        ]
      }
    },
    {
      "user": "0x0de4b96c9be779034397db6d339c5f92d5449662",
      "prizes": {
        "4": [
          22
        ],
        "5": [
          420,
          994
        ]
      }
    },
    {
      "user": "0x4f5755b3e27a7206564e9cf3578efff6e76c3531",
      "prizes": {
        "4": [
          35,
          40,
          48,
          65,
          84,
          88,
          126,
          169,
          188,
          213,
          216,
          218,
          255
        ],
        "5": [
          2,
          5,
          7,
          10,
          18,
          91,
          98,
          106,
          111,
          113,
          135,
          141,
          142,
          143,
          147,
          148,
          159,
          167,
          168,
          170,
          175,
          177,
          180,
          182,
          202,
          206,
          218,
          233,
          258,
          266,
          275,
          285,
          287,
          290,
          291,
          312,
          318,
          345,
          346,
          352,
          358,
          383,
          389,
          393,
          411,
          443,
          471,
          475,
          482,
          490,
          493,
          494,
          512,
          526,
          539,
          541,
          547,
          560,
          577,
          591,
          597,
          605,
          607,
          608,
          609,
          614,
          628,
          629,
          668,
          675,
          703,
          748,
          751,
          766,
          777,
          783,
          796,
          839,
          847,
          869,
          882,
          889,
          912,
          919,
          938,
          941,
          974,
          984,
          1016,
          1020
        ]
      }
    },
    {
      "user": "0xdb53fd872368c4d72ebb814b1e5d7b1babe2b834",
      "prizes": {
        "4": [
          65
        ],
        "5": [
          283,
          358,
          378,
          485,
          621,
          866
        ]
      }
    },
    {
      "user": "0x6b44862103b8a45f5ec701b69ec28a5d6d304950",
      "prizes": {
        "4": [
          37
        ],
        "5": [
          95
        ]
      }
    },
    {
      "user": "0x157c41a2a1b4e5810be2b009c093f3d78945c1db",
      "prizes": {
        "4": [
          48
        ]
      }
    },
    {
      "user": "0x1b52c00fd9dc204ad4e98c52c2b691f15acd1b60",
      "prizes": {
        "4": [
          158
        ]
      }
    },
    {
      "user": "0xd4fa23307a181b9ca567886eb5bcd5c8f8f8bb3e",
      "prizes": {
        "4": [
          216
        ],
        "5": [
          443
        ]
      }
    },
    {
      "user": "0x6d436d88dc7b6d66b4441781e8d9993bc13c27e3",
      "prizes": {
        "4": [
          4
        ],
        "5": [
          111,
          213,
          261,
          266,
          317,
          346,
          423,
          713,
          755,
          836,
          951
        ]
      }
    },
    {
      "user": "0x929a478b65ead807b8e3d1999db494dcff41b043",
      "prizes": {
        "4": [
          185
        ],
        "5": [
          247
        ]
      }
    },
    {
      "user": "0x58fa590e64ad0a2d8e24dcc229a5ca82d7d6af17",
      "prizes": {
        "4": [
          133
        ],
        "5": [
          672
        ]
      }
    },
    {
      "user": "0x2e1db2e75e05a7137b9386d0cecebea8a92187b5",
      "prizes": {
        "4": [
          11
        ],
        "5": [
          671,
          794,
          922,
          969,
          1022
        ]
      }
    },
    {
      "user": "0x60b897f671dc37713ec5cb7d62a8cfc8912c7df3",
      "prizes": {
        "4": [
          6
        ]
      }
    },
    {
      "user": "0xb5c305ce16f49c551e5b64f75e8150b62e629026",
      "prizes": {
        "4": [
          3,
          88,
          104
        ],
        "5": [
          47,
          242,
          286,
          306,
          337,
          358,
          412,
          506,
          611,
          630,
          762,
          773,
          797,
          843
        ]
      }
    },
    {
      "user": "0x2686544ed0149b134b27009958788cdf4ca8c064",
      "prizes": {
        "4": [
          28,
          80,
          171
        ],
        "5": [
          24,
          76,
          176,
          300,
          329,
          448,
          470,
          584,
          671,
          941,
          943,
          988
        ]
      }
    },
    {
      "user": "0x376d5c3a16e9d015e8c584bb2d278e25f0ccb27b",
      "prizes": {
        "4": [
          26,
          52,
          94,
          203
        ],
        "5": [
          53,
          114,
          159,
          214,
          256,
          321,
          469,
          828,
          1006,
          1014
        ]
      }
    },
    {
      "user": "0xbd15fbef966fe86aae4d10a6f98dad730db19b69",
      "prizes": {
        "4": [
          46
        ],
        "5": [
          934
        ]
      }
    },
    {
      "user": "0xfeeb4ed5029fa0febe1dbc87fe20ba1118dca49b",
      "prizes": {
        "4": [
          102,
          211
        ],
        "5": [
          119,
          253,
          284,
          633,
          719,
          912,
          992,
          994
        ]
      }
    },
    {
      "user": "0xce451698b148a74b43d2f038488bda5a319d3d29",
      "prizes": {
        "4": [
          32,
          43,
          107,
          111,
          123,
          135,
          158,
          168,
          180,
          239,
          240
        ],
        "5": [
          2,
          3,
          23,
          46,
          87,
          124,
          208,
          222,
          223,
          401,
          412,
          418,
          457,
          490,
          509,
          515,
          519,
          556,
          566,
          626,
          628,
          633,
          710,
          716,
          749,
          750,
          792,
          818,
          853,
          869,
          886,
          887,
          892,
          903,
          906,
          931,
          946,
          947,
          1014
        ]
      }
    },
    {
      "user": "0x3c1b7fb5d708ee1dc91f199fd9c2d8f3dba6c41d",
      "prizes": {
        "4": [
          13,
          38,
          58,
          73,
          89,
          113,
          119,
          124,
          140,
          185,
          196,
          206,
          236,
          238,
          242
        ],
        "5": [
          32,
          48,
          57,
          58,
          86,
          119,
          123,
          137,
          139,
          185,
          198,
          200,
          211,
          232,
          247,
          248,
          283,
          288,
          298,
          310,
          311,
          321,
          332,
          336,
          360,
          372,
          380,
          461,
          472,
          481,
          490,
          504,
          516,
          519,
          529,
          540,
          548,
          553,
          578,
          617,
          620,
          628,
          638,
          661,
          672,
          679,
          688,
          729,
          775,
          782,
          798,
          799,
          818,
          869,
          877,
          878,
          888,
          912,
          938,
          943,
          945,
          993,
          995,
          1002,
          1019
        ]
      }
    },
    {
      "user": "0xda9cb21f6b662eb972ecc8fd358a1fdab0811977",
      "prizes": {
        "4": [
          57
        ]
      }
    },
    {
      "user": "0x57a482ea32c7f75a9c0734206f5bd4f9bcb38e12",
      "prizes": {
        "4": [
          210
        ],
        "5": [
          158
        ]
      }
    },
    {
      "user": "0x89a7f580f121725644b3219949eaf256cb794afa",
      "prizes": {
        "4": [
          67
        ]
      }
    },
    {
      "user": "0x09080e4ffa4c08815cf53d157551cd409fe0a1f0",
      "prizes": {
        "4": [
          224,
          240
        ],
        "5": [
          103,
          183,
          443,
          460,
          474,
          782,
          814,
          1007,
          1023
        ]
      }
    },
    {
      "user": "0xa666ee932da1503601b364c18dd7d84391075e7e",
      "prizes": {
        "4": [
          18
        ]
      }
    },
    {
      "user": "0x4c0713d9eb4efd10ccf4d459630f4652723c9f30",
      "prizes": {
        "4": [
          45,
          67,
          161
        ],
        "5": [
          218,
          878,
          955,
          965
        ]
      }
    },
    {
      "user": "0x44af89b345b09aeeffc175bf43c2502d77e1a76a",
      "prizes": {
        "4": [
          73
        ]
      }
    },
    {
      "user": "0xaa8a19d6bf655bfa3c448248ad2482d05bab6f98",
      "prizes": {
        "4": [
          132
        ],
        "5": [
          891
        ]
      }
    },
    {
      "user": "0x6ce6986ff28bfed84a911682cdb127becb9fc88a",
      "prizes": {
        "4": [
          8,
          14,
          185,
          208,
          209
        ],
        "5": [
          13,
          294,
          330,
          390,
          439,
          456,
          539,
          555,
          561,
          603,
          623,
          636,
          724,
          797,
          928,
          936,
          965
        ]
      }
    },
    {
      "user": "0x48a7e4f10b34ad5b74eef2ae3f82b69783ec60c4",
      "prizes": {
        "4": [
          7
        ]
      }
    },
    {
      "user": "0x80fd2960e20776a4b7a9b7e6588178609bfa7a84",
      "prizes": {
        "4": [
          237
        ]
      }
    },
    {
      "user": "0xe47d91f4c4991d39a2f3a08baa7f1c296f0d72fd",
      "prizes": {
        "4": [
          145
        ]
      }
    },
    {
      "user": "0xa096f7d0aa83df9e41669629caf4ed435fe228e9",
      "prizes": {
        "4": [
          9
        ],
        "5": [
          401,
          449,
          512,
          549,
          595,
          610,
          649
        ]
      }
    },
    {
      "user": "0xf7467feb2c0b271dfffcdb9c928f0bf546575a87",
      "prizes": {
        "4": [
          55,
          64,
          87,
          92,
          129,
          149,
          198,
          206,
          223
        ],
        "5": [
          36,
          61,
          89,
          100,
          105,
          114,
          135,
          248,
          280,
          288,
          292,
          301,
          302,
          308,
          434,
          471,
          516,
          522,
          528,
          551,
          573,
          628,
          633,
          655,
          684,
          689,
          695,
          699,
          725,
          793,
          852,
          887,
          888,
          901,
          937,
          939,
          963,
          985,
          997,
          1003,
          1009
        ]
      }
    },
    {
      "user": "0x505aa104869783f1ed411339862a54041eb57162",
      "prizes": {
        "4": [
          156
        ],
        "5": [
          702,
          891
        ]
      }
    },
    {
      "user": "0xafa4d9b35ff0b4dc94d5f17b6dac3017df6f1a5c",
      "prizes": {
        "4": [
          172
        ],
        "5": [
          293,
          460,
          482,
          682,
          966,
          1014,
          1015
        ]
      }
    },
    {
      "user": "0x7b22fda532f9f9fb688e502d4caf7b2b9bd36a26",
      "prizes": {
        "4": [
          52,
          112,
          142,
          183,
          189,
          213,
          214
        ],
        "5": [
          8,
          18,
          37,
          52,
          62,
          64,
          89,
          106,
          134,
          155,
          168,
          185,
          201,
          208,
          248,
          259,
          271,
          293,
          306,
          330,
          351,
          372,
          389,
          398,
          431,
          447,
          455,
          458,
          462,
          472,
          494,
          498,
          530,
          656,
          658,
          728,
          768,
          878,
          881,
          882,
          928,
          976,
          986,
          996,
          1013
        ]
      }
    },
    {
      "user": "0x85fbec0d141722b596121ec3e53765f35731c502",
      "prizes": {
        "4": [
          62,
          118,
          166
        ],
        "5": [
          207,
          211,
          311,
          984
        ]
      }
    },
    {
      "user": "0xa9f8275ec69918e26e936be48c1418fe533d0a5a",
      "prizes": {
        "4": [
          27,
          44,
          48,
          59,
          63,
          68,
          104,
          109,
          112,
          115,
          126,
          151,
          173,
          176,
          193,
          234,
          245
        ],
        "5": [
          5,
          21,
          71,
          84,
          105,
          131,
          147,
          158,
          159,
          177,
          192,
          202,
          222,
          225,
          228,
          243,
          244,
          255,
          258,
          279,
          281,
          285,
          287,
          298,
          343,
          366,
          385,
          393,
          400,
          407,
          411,
          468,
          473,
          504,
          522,
          550,
          551,
          574,
          584,
          587,
          622,
          719,
          724,
          787,
          802,
          821,
          830,
          831,
          834,
          840,
          842,
          856,
          859,
          868,
          886,
          888,
          897,
          902,
          924,
          935,
          943,
          944,
          965,
          979,
          999,
          1002,
          1015,
          1019
        ]
      }
    },
    {
      "user": "0x0b28cb4281a584ace7f550e2b2cd6238d5f1684c",
      "prizes": {
        "4": [
          254
        ],
        "5": [
          59,
          768
        ]
      }
    },
    {
      "user": "0xebcadf08f64012787f2f4dde99b13fe1183b72e2",
      "prizes": {
        "4": [
          117
        ]
      }
    },
    {
      "user": "0x32ad379d17a523c79cba370a2bd645637ed4f4af",
      "prizes": {
        "4": [
          203
        ]
      }
    },
    {
      "user": "0x0994e680bcbec9f3701734f21c4487f05893e104",
      "prizes": {
        "4": [
          215
        ]
      }
    },
    {
      "user": "0x7af5a23d180e6dff260b3b241a253a90f0ff8048",
      "prizes": {
        "4": [
          198
        ],
        "5": [
          149
        ]
      }
    },
    {
      "user": "0x8e49d2574042611cf30551e90d37d7b2c08b7028",
      "prizes": {
        "4": [
          33,
          34,
          38,
          45,
          50,
          77,
          150,
          171,
          193,
          214,
          251
        ],
        "5": [
          74,
          89,
          175,
          176,
          192,
          217,
          229,
          255,
          271,
          325,
          329,
          371,
          374,
          388,
          428,
          464,
          492,
          495,
          530,
          555,
          575,
          590,
          624,
          626,
          628,
          630,
          637,
          692,
          703,
          724,
          725,
          756,
          760,
          761,
          771,
          779,
          783,
          801,
          820,
          867,
          871,
          907,
          940,
          942,
          965,
          1015
        ]
      }
    },
    {
      "user": "0xd8b53858ba1cba48b7612ba8b91b9447f3163ec4",
      "prizes": {
        "5": [
          635
        ]
      }
    },
    {
      "user": "0xedd16f9d9c994e2a930068515676908acc74e6f3",
      "prizes": {
        "5": [
          762
        ]
      }
    },
    {
      "user": "0xd8adba33d0059d8978087a6ef68690d80add0b29",
      "prizes": {
        "5": [
          593
        ]
      }
    },
    {
      "user": "0x4d1243b6f45d209bd59be55be1609219fd93dc3c",
      "prizes": {
        "5": [
          769
        ]
      }
    },
    {
      "user": "0x3350692c81dd3a8dbeb46fd3042908ffd0c3e60c",
      "prizes": {
        "5": [
          691
        ]
      }
    },
    {
      "user": "0xa8078cabce440b0feadd7264adf179d301fcef18",
      "prizes": {
        "5": [
          700
        ]
      }
    },
    {
      "user": "0xe3da901f1d077f2bacb3c3938234cd7dcc6c7a9c",
      "prizes": {
        "5": [
          770
        ]
      }
    },
    {
      "user": "0x55dbcba09d2e230f413b4bf7aea1b0feb3fcfaef",
      "prizes": {
        "5": [
          53,
          208
        ]
      }
    },
    {
      "user": "0xe48dd2a322a7ebfdaa9680fd2e8cec27cbb7a765",
      "prizes": {
        "5": [
          139,
          560,
          957
        ]
      }
    },
    {
      "user": "0x63f59dfe5a12be4ecab6ad0ecca568531077af42",
      "prizes": {
        "5": [
          280,
          870
        ]
      }
    },
    {
      "user": "0x5add08b293702e40c24876db430cb1f36099795f",
      "prizes": {
        "5": [
          382
        ]
      }
    },
    {
      "user": "0x91b34e88d44fb4c15a5faa04005a48fd5f5e7eea",
      "prizes": {
        "5": [
          118,
          560
        ]
      }
    },
    {
      "user": "0xb03f5438f9a243de5c3b830b7841ec315034cd5f",
      "prizes": {
        "5": [
          163
        ]
      }
    },
    {
      "user": "0x06360f0a6c52cba7c76cfe9a5c940c75a4d9a330",
      "prizes": {
        "5": [
          879
        ]
      }
    },
    {
      "user": "0x4427788a485b0b64675a8316b3658cd172bcc6ef",
      "prizes": {
        "5": [
          923
        ]
      }
    },
    {
      "user": "0xf8445b5ee5167c5d5ab91e29dc542851295f9b17",
      "prizes": {
        "5": [
          986
        ]
      }
    },
    {
      "user": "0x0865c770922324a7ffeae432cae6718cd3adac8f",
      "prizes": {
        "5": [
          672
        ]
      }
    },
    {
      "user": "0x22145b2537edb0a45455b3bee3fe2aab2f27c598",
      "prizes": {
        "5": [
          218,
          497
        ]
      }
    },
    {
      "user": "0x37cdd2229274a8a0087384811f029e1ab8fdd581",
      "prizes": {
        "5": [
          251
        ]
      }
    },
    {
      "user": "0x2d93f264370bf61f8759470a906528ad6937a47a",
      "prizes": {
        "5": [
          576
        ]
      }
    },
    {
      "user": "0xd4c4d64c869d2fa58cbebae162ca386669d854db",
      "prizes": {
        "5": [
          70
        ]
      }
    },
    {
      "user": "0xbb9eb595c956927fbc0638414736f30cb030c4c6",
      "prizes": {
        "5": [
          545
        ]
      }
    },
    {
      "user": "0x803585733d4554e712dcacc2acea3a23b96de1e0",
      "prizes": {
        "5": [
          246,
          849
        ]
      }
    },
    {
      "user": "0x093e4ab2665d17e66eff0e79460cb53659195275",
      "prizes": {
        "5": [
          531
        ]
      }
    },
    {
      "user": "0xbf4c544b70100d72c5c40e4521b600fe62a22b87",
      "prizes": {
        "5": [
          40,
          181
        ]
      }
    },
    {
      "user": "0x40de6f599eeaf9d1977291a0ab2698e67e5f4099",
      "prizes": {
        "5": [
          136
        ]
      }
    },
    {
      "user": "0x7998bcb66e51a49be8e31a31b957bcd02c8ded6e",
      "prizes": {
        "5": [
          149,
          867
        ]
      }
    },
    {
      "user": "0xdd45ca901067d65860b54d4310e37371cd92fb09",
      "prizes": {
        "5": [
          908
        ]
      }
    },
    {
      "user": "0xd917eb4dcfccf91e6496702bc6309d5a59eef713",
      "prizes": {
        "5": [
          164,
          321,
          555,
          558,
          951
        ]
      }
    },
    {
      "user": "0x175c4f84f41bd3dc37a42d8260f57bc5475e9753",
      "prizes": {
        "5": [
          331,
          710,
          793
        ]
      }
    },
    {
      "user": "0x423b1e15261045fc8266e91171cd5bed81c7444f",
      "prizes": {
        "5": [
          155
        ]
      }
    },
    {
      "user": "0x912a1bea60621a6e6d9bfece1af9cdf2392bf65d",
      "prizes": {
        "5": [
          636
        ]
      }
    },
    {
      "user": "0xd836da33a6629548271eb9ef4f62d083376eb4a6",
      "prizes": {
        "5": [
          130
        ]
      }
    },
    {
      "user": "0xc9a2ba82b78fd8d85aa265f6a6cd3a1054350ca4",
      "prizes": {
        "5": [
          847
        ]
      }
    },
    {
      "user": "0xa6e103824673013dce211f683551ce18cdc1e3b3",
      "prizes": {
        "5": [
          6
        ]
      }
    },
    {
      "user": "0x39514af81df633096df1ccc1e5a5daa2f2330486",
      "prizes": {
        "5": [
          25
        ]
      }
    },
    {
      "user": "0x4547f0133001991cbf7c4055a7bec5bae57331e4",
      "prizes": {
        "5": [
          427,
          555,
          837
        ]
      }
    },
    {
      "user": "0x52f5a21510fb472774469edd718911b01e280b31",
      "prizes": {
        "5": [
          825
        ]
      }
    },
    {
      "user": "0x2225b32aebf89888821ec7dd59dcbc653b49f6aa",
      "prizes": {
        "5": [
          925,
          1018
        ]
      }
    },
    {
      "user": "0x417372e4d116b6af9e6fbd0d1d16f1483f52f6e8",
      "prizes": {
        "5": [
          337,
          437
        ]
      }
    },
    {
      "user": "0x62068e6e29642d52ba9d8c6a655e3b225cfb6e2d",
      "prizes": {
        "5": [
          492
        ]
      }
    },
    {
      "user": "0xd167ce49b3cf9392a3f8893c9a29ebc3195b6a3e",
      "prizes": {
        "5": [
          583,
          654
        ]
      }
    },
    {
      "user": "0x0d3d681762f9eda9541fab6acfb17c50025b630b",
      "prizes": {
        "5": [
          26,
          526,
          905
        ]
      }
    },
    {
      "user": "0x8a2291a0597671942a91782451ef8559165f3702",
      "prizes": {
        "5": [
          845
        ]
      }
    },
    {
      "user": "0xd9e7c440039a9c99b175de70cecaf1b7be8f121b",
      "prizes": {
        "5": [
          270,
          306,
          350
        ]
      }
    },
    {
      "user": "0xd38472d93011d266494136035bb9f663002290a3",
      "prizes": {
        "5": [
          870
        ]
      }
    },
    {
      "user": "0xd4785e5e90929af38edc514a8a860691cca606ad",
      "prizes": {
        "5": [
          55,
          155,
          234,
          253,
          593
        ]
      }
    },
    {
      "user": "0xd914fadffcf805292d74221852e0debfebc682d7",
      "prizes": {
        "5": [
          176,
          178,
          532,
          815,
          846
        ]
      }
    },
    {
      "user": "0xebef7c82957264737745c11b6892b512e0cbea3e",
      "prizes": {
        "5": [
          351,
          382,
          580,
          763
        ]
      }
    },
    {
      "user": "0x4d44764e509fe153c80ff90d403b391aefa23e5f",
      "prizes": {
        "5": [
          417
        ]
      }
    },
    {
      "user": "0x4e42bd9e46444146c6ae31bc301f0ab7cf623ee7",
      "prizes": {
        "5": [
          695
        ]
      }
    },
    {
      "user": "0x411b60da6a86ffdd0590083e3c29e48c17095638",
      "prizes": {
        "5": [
          975
        ]
      }
    },
    {
      "user": "0x5c9db9f19c35130c696e19ab60fbb8955ddaf29d",
      "prizes": {
        "5": [
          107,
          408
        ]
      }
    },
    {
      "user": "0x3d6facad1f5c6463e592c94a2a316a7697ad9de0",
      "prizes": {
        "5": [
          852
        ]
      }
    },
    {
      "user": "0xacfdff61776531f64dbe50ad196f95a1cf92a8d5",
      "prizes": {
        "5": [
          263,
          301,
          614
        ]
      }
    },
    {
      "user": "0x2cdce14d479a2d0aa40e974553dd3ecb65a77b05",
      "prizes": {
        "5": [
          213,
          337,
          866
        ]
      }
    },
    {
      "user": "0xc8a1f9af0d596ca08e5779eaf7c09b133d7b41b8",
      "prizes": {
        "5": [
          726,
          747
        ]
      }
    },
    {
      "user": "0x9f36a6bb398118bdcd5b1bc3343d8feb6d7d02b9",
      "prizes": {
        "5": [
          725,
          811
        ]
      }
    },
    {
      "user": "0x7ebd5f813e9bac793fba073e98bc06ae89763eec",
      "prizes": {
        "5": [
          32
        ]
      }
    },
    {
      "user": "0x1713e003c129b39d594b2857e6b1d9bae33d6770",
      "prizes": {
        "5": [
          125,
          226,
          325,
          404,
          406,
          502,
          683
        ]
      }
    },
    {
      "user": "0xf112f84c28795172cf998ea5d2a5993f78ccbddf",
      "prizes": {
        "5": [
          31
        ]
      }
    },
    {
      "user": "0x430e225f43549f9ad06e5e68137bec8bb4071f97",
      "prizes": {
        "5": [
          440,
          855
        ]
      }
    },
    {
      "user": "0xb6664e200f4d9e71b4f6cf0be286a2b796915d54",
      "prizes": {
        "5": [
          456,
          852
        ]
      }
    },
    {
      "user": "0x6347f15d4337daf377c332d7cae7663086925648",
      "prizes": {
        "5": [
          388
        ]
      }
    },
    {
      "user": "0x5584541f0fd8561455c211e10b5c9750fdd62fbb",
      "prizes": {
        "5": [
          93
        ]
      }
    },
    {
      "user": "0xc0b7d5d85e1425fbdbab0b9b66f02985f9b9b530",
      "prizes": {
        "5": [
          700
        ]
      }
    },
    {
      "user": "0xe574c8c474beaf5413f404894eee7432856d28fd",
      "prizes": {
        "5": [
          914
        ]
      }
    },
    {
      "user": "0xbd4f481847ced55203ce7a3c3fde98da691601c7",
      "prizes": {
        "5": [
          88
        ]
      }
    },
    {
      "user": "0x5a31722a0687b09c8332b2d61c2f4566de14ad00",
      "prizes": {
        "5": [
          40,
          936
        ]
      }
    },
    {
      "user": "0x866af07715054c4f387d60dd4e1c2882e9040b70",
      "prizes": {
        "5": [
          238
        ]
      }
    },
    {
      "user": "0x41f0f58c59b61fdea51c1901a316838e1311bfee",
      "prizes": {
        "5": [
          679
        ]
      }
    },
    {
      "user": "0xe09c035a9751b594a6d0dc8a4ef9c1f1139ebad2",
      "prizes": {
        "5": [
          823
        ]
      }
    },
    {
      "user": "0x2a131a477467e1998fe7290a1f5377f51cb8238d",
      "prizes": {
        "5": [
          425
        ]
      }
    }
  ],
  "0x051264d4c1a576cb423c350c973fe0b748e4170f": [],
  "0x11271bf9855b679bc484a0c80a69d8cc72fcef89": [
    {
      "user": "0xd00722a5a5a3b0e3d2b4b6e154aa103d457e1a5f",
      "prizes": {
        "5": [
          811
        ]
      }
    },
    {
      "user": "0xc3f6e18b429b6baf1bd31b1e504aee7827c7aab5",
      "prizes": {
        "5": [
          975
        ]
      }
    },
    {
      "user": "0xb4212f7cb18cd97dd17190106f208af86d288eb7",
      "prizes": {
        "5": [
          182
        ]
      }
    },
    {
      "user": "0x01d9212ad932386f3ddea568291f109e8c0b66b1",
      "prizes": {
        "5": [
          68,
          542
        ]
      }
    },
    {
      "user": "0x39d03d8e03e2627fa027149f43d1caece1dcb4f2",
      "prizes": {
        "5": [
          382,
          971
        ]
      }
    },
    {
      "user": "0x5584541f0fd8561455c211e10b5c9750fdd62fbb",
      "prizes": {
        "4": [
          136
        ],
        "5": [
          323
        ]
      }
    },
    {
      "user": "0x6d436d88dc7b6d66b4441781e8d9993bc13c27e3",
      "prizes": {
        "4": [
          176,
          184
        ],
        "5": [
          81,
          993
        ]
      }
    },
    {
      "user": "0x8a1ec127978bcc7499b2a188df2bd1810f522ac7",
      "prizes": {
        "4": [
          90,
          187
        ],
        "5": [
          204,
          322,
          540
        ]
      }
    },
    {
      "user": "0xa555cf7e7e04919e653577ff76fe44e119a018cc",
      "prizes": {
        "5": [
          567
        ]
      }
    },
    {
      "user": "0x6ce6986ff28bfed84a911682cdb127becb9fc88a",
      "prizes": {
        "5": [
          138,
          795
        ]
      }
    },
    {
      "user": "0x5d65804dfebd24266596ee62e49cc78d35b752eb",
      "prizes": {
        "5": [
          614
        ]
      }
    },
    {
      "user": "0xd9ec650cfbc557f03c565f5189ec31fedbee43a5",
      "prizes": {
        "4": [
          180
        ],
        "5": [
          67,
          492,
          965
        ]
      }
    },
    {
      "user": "0x51bc9862ad17023fa88435f51fcaa6e677b2ca97",
      "prizes": {
        "4": [
          14,
          18,
          159,
          166,
          238,
          255
        ],
        "5": [
          4,
          369,
          405,
          435,
          454,
          516,
          523,
          541,
          781,
          850,
          864,
          897,
          926,
          945
        ]
      }
    },
    {
      "user": "0x38190e4df6dfda78297e50cd831ceaa3e00c715e",
      "prizes": {
        "4": [
          51,
          110
        ],
        "5": [
          767
        ]
      }
    },
    {
      "user": "0x57a482ea32c7f75a9c0734206f5bd4f9bcb38e12",
      "prizes": {
        "4": [
          175
        ]
      }
    }
  ],
  "0x171d898849cd21a1ca6e111933dad1f5b8664c88": [],
  "0x182d3050f7261494757638ff3345c7163e5990f3": [],
  "0x1f16d3ccf568e96019cedc8a2c79d2ca6257894e": [
    {
      "user": "0x97116661c85c4e1ee35aa10f7fc5fe5e67b83a5b",
      "prizes": {
        "5": [
          239
        ]
      }
    },
    {
      "user": "0x0aaf37c3eaaa42d417434fd2cec555846d46415c",
      "prizes": {
        "5": [
          479
        ]
      }
    },
    {
      "user": "0x7b22fda532f9f9fb688e502d4caf7b2b9bd36a26",
      "prizes": {
        "5": [
          332,
          737,
          792,
          801
        ]
      }
    },
    {
      "user": "0x0d8163aee1bec6338b979e34b6cb31013fe82516",
      "prizes": {
        "5": [
          184,
          325,
          551,
          781,
          925
        ]
      }
    },
    {
      "user": "0x7928a66320e3799a935a877a70eb8567b7c17a75",
      "prizes": {
        "5": [
          643
        ]
      }
    }
  ],
  "0x2998c1685e308661123f64b333767266035f5020": [
    {
      "user": "0xe0e7b7c5ae92fe94d2ae677d81214d6ad7a11c27",
      "prizes": {
        "4": [
          131
        ],
        "5": [
          799,
          947
        ]
      }
    },
    {
      "user": "0x501d66e0b4254de6187443b9cdb744e2752f489e",
      "prizes": {
        "4": [
          27
        ]
      }
    },
    {
      "user": "0x74a5c89b08e7e719384ea230591187d041f68c88",
      "prizes": {
        "4": [
          237
        ],
        "5": [
          294
        ]
      }
    },
    {
      "user": "0x174976a7bae6bf9abb80a7bd6896a78fbd17386d",
      "prizes": {
        "4": [
          47,
          68,
          78,
          161,
          173,
          198,
          207,
          240
        ],
        "5": [
          32,
          76,
          89,
          163,
          184,
          232,
          265,
          267,
          360,
          361,
          449,
          492,
          535,
          544,
          562,
          573,
          589,
          622,
          628,
          733,
          851,
          903
        ]
      }
    },
    {
      "user": "0x3d713067761725e6a237e5a0572aa47348eafe3d",
      "prizes": {
        "4": [
          153,
          240
        ],
        "5": [
          62,
          76,
          110,
          112,
          131,
          261,
          285,
          305,
          344,
          352,
          419,
          629,
          712,
          780,
          809,
          831,
          840,
          871,
          930,
          934
        ]
      }
    },
    {
      "user": "0xd70804463bb2760c3384fc87bbe779e3d91bab3a",
      "prizes": {
        "4": [
          161
        ],
        "5": [
          21,
          365,
          457,
          626,
          646,
          966
        ]
      }
    },
    {
      "user": "0x3d6facad1f5c6463e592c94a2a316a7697ad9de0",
      "prizes": {
        "4": [
          106
        ]
      }
    },
    {
      "user": "0x675233348fc519cbcf70fe75c26856501327fee1",
      "prizes": {
        "4": [
          81,
          209
        ],
        "5": [
          423,
          643
        ]
      }
    },
    {
      "user": "0xfb96d3340ab2452955f667615c9f51115ae55dcc",
      "prizes": {
        "4": [
          46
        ]
      }
    },
    {
      "user": "0x79e09a74f03b0683a950887e2387cffbf244d497",
      "prizes": {
        "4": [
          66,
          183
        ],
        "5": [
          346
        ]
      }
    },
    {
      "user": "0x44989d681071171956445bc2a8e00d614e3358c0",
      "prizes": {
        "4": [
          203,
          206
        ],
        "5": [
          184,
          192,
          286,
          321,
          573,
          686,
          865,
          904
        ]
      }
    },
    {
      "user": "0x1a59e9c02ec869065e301cfcc0ce7835e94ec07f",
      "prizes": {
        "4": [
          250
        ]
      }
    },
    {
      "user": "0x8ae715283ed6617963c0001c3074f574dbb70d9a",
      "prizes": {
        "4": [
          99
        ],
        "5": [
          145
        ]
      }
    },
    {
      "user": "0x44704724fd058ca0c6f3b3ad2b06de65110f4c26",
      "prizes": {
        "4": [
          57,
          178,
          208
        ],
        "5": [
          141,
          148,
          877,
          931
        ]
      }
    },
    {
      "user": "0x6156ec8cafc48f50f2747a4dad9c0937c0d1c459",
      "prizes": {
        "4": [
          177
        ],
        "5": [
          677,
          815,
          963
        ]
      }
    },
    {
      "user": "0xd9e1bf544ae98c663e108b6c9e0037fd96055b5f",
      "prizes": {
        "4": [
          194
        ],
        "5": [
          290
        ]
      }
    },
    {
      "user": "0x57a482ea32c7f75a9c0734206f5bd4f9bcb38e12",
      "prizes": {
        "4": [
          249
        ]
      }
    },
    {
      "user": "0x223310371e98755a35756ea24b629113584a8d9d",
      "prizes": {
        "5": [
          557
        ]
      }
    },
    {
      "user": "0xab4382aadae5bf4b37b90b9dc07fc72d52e2a28a",
      "prizes": {
        "5": [
          838,
          862
        ]
      }
    },
    {
      "user": "0xfeeb4ed5029fa0febe1dbc87fe20ba1118dca49b",
      "prizes": {
        "5": [
          186,
          293,
          498,
          789,
          923
        ]
      }
    },
    {
      "user": "0xf05e4f44de569cf8c6acf5fce98271008a532969",
      "prizes": {
        "5": [
          231,
          721
        ]
      }
    },
    {
      "user": "0xe06df8ad4c63cc27454af2ce3a722621f680ce77",
      "prizes": {
        "5": [
          457
        ]
      }
    },
    {
      "user": "0x0bd274078c80950a4222d521474abaf6e1cc75a2",
      "prizes": {
        "5": [
          491
        ]
      }
    },
    {
      "user": "0xad2d5bdc3c2dd575c0fa8b70b4f9dfc74b5c1590",
      "prizes": {
        "5": [
          64,
          74,
          118,
          193,
          288,
          408,
          486,
          542,
          687,
          750,
          837,
          960
        ]
      }
    },
    {
      "user": "0x7998bcb66e51a49be8e31a31b957bcd02c8ded6e",
      "prizes": {
        "5": [
          47,
          52,
          419
        ]
      }
    },
    {
      "user": "0xf77e2c9b9ea81843d97a034e50aaa61b54edcc92",
      "prizes": {
        "5": [
          39
        ]
      }
    },
    {
      "user": "0x42b1d175e813c143314864da54453920e7d60e2b",
      "prizes": {
        "5": [
          208
        ]
      }
    },
    {
      "user": "0x2f358e304115bb32ec76899965fc5b91a23cabe1",
      "prizes": {
        "5": [
          126,
          197
        ]
      }
    },
    {
      "user": "0xd914fadffcf805292d74221852e0debfebc682d7",
      "prizes": {
        "5": [
          887
        ]
      }
    },
    {
      "user": "0x6b44862103b8a45f5ec701b69ec28a5d6d304950",
      "prizes": {
        "5": [
          372
        ]
      }
    },
    {
      "user": "0xde981d36d4d60d08b344c6e780a90de3ff717648",
      "prizes": {
        "5": [
          1
        ]
      }
    },
    {
      "user": "0x2e1db2e75e05a7137b9386d0cecebea8a92187b5",
      "prizes": {
        "3": [
          56
        ],
        "5": [
          147,
          645,
          725,
          834
        ]
      }
    },
    {
      "user": "0x139f7e58c4ba8c98d45ef9fcbe2ddce810002baa",
      "prizes": {
        "5": [
          130,
          318
        ]
      }
    },
    {
      "user": "0x66cfd050e328737f3e9ad9262c068c5b2ba4390b",
      "prizes": {
        "5": [
          235,
          539,
          638,
          679,
          686,
          986
        ]
      }
    },
    {
      "user": "0xa6e029548152f098416c0ad60c18930b4f8619c6",
      "prizes": {
        "3": [
          45
        ],
        "5": [
          157,
          518,
          561
        ]
      }
    },
    {
      "user": "0x5dea60eef2bfcef3a808a219b562145d1b80bd7d",
      "prizes": {
        "5": [
          154
        ]
      }
    },
    {
      "user": "0x979b0b34a360e7a401d46e83c4b23dda54998da4",
      "prizes": {
        "5": [
          655
        ]
      }
    },
    {
      "user": "0x1acd732f430fe43814130d349715f8829ad65536",
      "prizes": {
        "5": [
          903
        ]
      }
    },
    {
      "user": "0x9f36a6bb398118bdcd5b1bc3343d8feb6d7d02b9",
      "prizes": {
        "5": [
          37,
          69,
          135,
          808
        ]
      }
    },
    {
      "user": "0x958c90647b2e6d1fcb714886435ab84391fcd15a",
      "prizes": {
        "5": [
          836
        ]
      }
    },
    {
      "user": "0xf45ce3921f25677802b0f32b1664ba55535264be",
      "prizes": {
        "5": [
          927
        ]
      }
    },
    {
      "user": "0x897d24557116f39440fab68feb0ed97bbbeaeeed",
      "prizes": {
        "5": [
          849
        ]
      }
    },
    {
      "user": "0xa38445311ccd04a54183cdd347e793f4d548df3f",
      "prizes": {
        "5": [
          691
        ]
      }
    },
    {
      "user": "0xa8033118b5393bceda847e62eb69a03188cb4a89",
      "prizes": {
        "5": [
          33,
          973
        ]
      }
    },
    {
      "user": "0x7692a4436f8252f34258c2bfa846ec5e840d5e55",
      "prizes": {
        "5": [
          341,
          434
        ]
      }
    }
  ],
  "0x2a015a66dd75b60423414d508078e8666b7771d7": [],
  "0x35b92060f56cc9be483c91a581647387ff3e5c84": [],
  "0x363b7a1567af0dbf06642c4028779c3f3365b516": [],
  "0x37e49c9dbf195f5d436c7a7610fe703cdcd8147b": [],
  "0x395ae52bb17aef68c2888d941736a71dc6d4e125": [],
  "0x3d87b066dcf93661c66cd5158a449483259a3bc1": [],
  "0x3e8dbe51da479f7e8ac46307af99ad5b4b5b41dc": [
    {
      "user": "0x6eba83ac495f7db36f398aeffbcd0fb6f21aab7e",
      "prizes": {
        "4": [
          171
        ],
        "5": [
          967
        ]
      }
    },
    {
      "user": "0xd53d36f66ca025bbe2a089f5dc59e3235c4327d3",
      "prizes": {
        "4": [
          219
        ],
        "5": [
          332,
          338,
          605,
          828
        ]
      }
    },
    {
      "user": "0x0d3d681762f9eda9541fab6acfb17c50025b630b",
      "prizes": {
        "4": [
          79
        ],
        "5": [
          340,
          374,
          678
        ]
      }
    },
    {
      "user": "0x9b2247e137387c2a2c49e9607e4b70473891e9fc",
      "prizes": {
        "4": [
          179
        ],
        "5": [
          207,
          774
        ]
      }
    },
    {
      "user": "0xf45ce3921f25677802b0f32b1664ba55535264be",
      "prizes": {
        "4": [
          132
        ],
        "5": [
          320
        ]
      }
    },
    {
      "user": "0xa6e029548152f098416c0ad60c18930b4f8619c6",
      "prizes": {
        "4": [
          134,
          185
        ],
        "5": [
          113
        ]
      }
    },
    {
      "user": "0x8aeb24ba4a9f25ead8609ee3bc6f52ac8d49ad3b",
      "prizes": {
        "4": [
          215
        ]
      }
    },
    {
      "user": "0x57a482ea32c7f75a9c0734206f5bd4f9bcb38e12",
      "prizes": {
        "5": [
          853
        ]
      }
    },
    {
      "user": "0xbb7724d5fc4af70489b66d13b4f19361b1e31457",
      "prizes": {
        "5": [
          217,
          693,
          740,
          763
        ]
      }
    },
    {
      "user": "0x5e397021f3c38f594e5c8a2ec8ec79faf6145c8c",
      "prizes": {
        "5": [
          663
        ]
      }
    },
    {
      "user": "0x93cebc03c6587f3943d36a4d14f073740a049262",
      "prizes": {
        "5": [
          242
        ]
      }
    },
    {
      "user": "0x6fbe01fd68289ace7ecaca15d465b47c244bbf92",
      "prizes": {
        "5": [
          1004
        ]
      }
    },
    {
      "user": "0x32bd500a8d5431cdad7be26648c153f3c57bd73b",
      "prizes": {
        "5": [
          622
        ]
      }
    },
    {
      "user": "0x936d802a8c0943bf984a95159bd7b6b6650f5c77",
      "prizes": {
        "5": [
          562,
          595
        ]
      }
    },
    {
      "user": "0xc632b0c926291da28f8496d4f33cbe1f454e6f64",
      "prizes": {
        "5": [
          661,
          941
        ]
      }
    },
    {
      "user": "0x9f36a6bb398118bdcd5b1bc3343d8feb6d7d02b9",
      "prizes": {
        "5": [
          367,
          898
        ]
      }
    }
  ],
  "0x4200000000000000000000000000000000000042": [],
  "0x426783a67d34149c5fd13ab233de4caf5f7ca7b6": [],
  "0x449b6a60501015c1a8fda6cd97147280f5eb33d7": [
    {
      "user": "0xe9fd3fea5a33360d78fd5ee713e71a75f87b09b6",
      "prizes": {
        "4": [
          134
        ],
        "5": [
          238,
          876
        ]
      }
    },
    {
      "user": "0x1a59e9c02ec869065e301cfcc0ce7835e94ec07f",
      "prizes": {
        "5": [
          230
        ]
      }
    },
    {
      "user": "0x7692a4436f8252f34258c2bfa846ec5e840d5e55",
      "prizes": {
        "5": [
          746
        ]
      }
    },
    {
      "user": "0xc694108e704b3ac3c5b099a4b06208bd0695ad00",
      "prizes": {
        "5": [
          335
        ]
      }
    }
  ],
  "0x46ec15aed8645154a3a276c007ac5b99d8d7067c": [],
  "0x4b9a4edbdb67ee8d880964732c1f56e4c13f2c04": [],
  "0x5c458df58c2a4253f07ae416e8828ccbdbb2974a": [],
  "0x5eb32e6dec24d58c14d21fd1b329d9f65de58364": [],
  "0x5fbfe2ef7f7396269356ce3bb673fc3fdd2c3468": [],
  "0x5fd190357eccf07f558e48f1f85ed184ee211e53": [],
  "0x61c15203aa2745d5fda730268cb4efa46b962db0": [],
  "0x626f8282f712732be0c12d4a89a86be6e9ce8ac8": [],
  "0x7889366a039d92dd6aa12ce8f6fb027c3b7e397c": [],
  "0x7affb8cb92ddf9f9d0ba6fdcd7cd7905cb6d2ec1": [],
  "0x896232c67eba02033334008f21767fe586792c52": [],
  "0x8b47c737179cb1354e8950acec6bd43f26af0290": [],
  "0x8c2f27b7819eb1bb7e3b5c407c5e1839186d5aba": [],
  "0x934c51eedbd0d558ab1c171498271930b4716295": [],
  "0x9b4c0de59628c64b02d7ce86f21db9a579539d5a": [],
  "0x9b53ef6f13077727d22cb4acad1119c79a97be17": [
    {
      "user": "0x48a7e4f10b34ad5b74eef2ae3f82b69783ec60c4",
      "prizes": {
        "5": [
          842
        ]
      }
    },
    {
      "user": "0x1da341e5ea71ec05e472b674b046bf631441d211",
      "prizes": {
        "5": [
          659
        ]
      }
    },
    {
      "user": "0x6181b92270ad96b4e080d456d54cfddb1c32cad9",
      "prizes": {
        "5": [
          376
        ]
      }
    },
    {
      "user": "0x9b53ef6f13077727d22cb4acad1119c79a97be17",
      "prizes": {
        "4": [
          35,
          58,
          65,
          66,
          152,
          198,
          242
        ],
        "5": [
          49,
          69,
          136,
          144,
          249,
          311,
          419,
          565,
          594,
          641,
          661,
          682,
          882,
          916,
          948,
          967,
          980,
          1009
        ]
      }
    },
    {
      "user": "0x29bbf26fc9628d076094c20f0cea51142bbc4aa5",
      "prizes": {
        "4": [
          133,
          141,
          173,
          220,
          239
        ],
        "5": [
          28,
          151,
          160,
          189,
          268,
          280,
          317,
          336,
          433,
          451,
          463,
          541,
          560,
          645,
          705,
          740,
          761,
          771,
          775,
          805,
          814,
          907,
          921,
          951,
          974,
          981,
          1003
        ]
      }
    },
    {
      "user": "0x02fb37f0c8d6ebd4e2726e7914e20bb648c62418",
      "prizes": {
        "5": [
          63
        ]
      }
    },
    {
      "user": "0xc93c3c7d65c191a76b6db9e2bfb76dba9c6c6011",
      "prizes": {
        "5": [
          274
        ]
      }
    },
    {
      "user": "0x3d713067761725e6a237e5a0572aa47348eafe3d",
      "prizes": {
        "4": [
          132
        ]
      }
    },
    {
      "user": "0xc9a2ba82b78fd8d85aa265f6a6cd3a1054350ca4",
      "prizes": {
        "4": [
          144
        ]
      }
    },
    {
      "user": "0x3630a6b345878549694e9161cd22550fce73d3bd",
      "prizes": {
        "4": [
          177
        ]
      }
    }
  ],
  "0xa46de5b77dbe59a7b9213f3dd1634da25e7e3bfb": [],
  "0xa52e38a9147f5ea9e0c5547376c21c9e3f3e5e1f": [
    {
      "user": "0x5584541f0fd8561455c211e10b5c9750fdd62fbb",
      "prizes": {
        "5": [
          246
        ]
      }
    },
    {
      "user": "0x174976a7bae6bf9abb80a7bd6896a78fbd17386d",
      "prizes": {
        "5": [
          39
        ]
      }
    },
    {
      "user": "0x29bbf26fc9628d076094c20f0cea51142bbc4aa5",
      "prizes": {
        "4": [
          240
        ],
        "5": [
          329,
          387
        ]
      }
    },
    {
      "user": "0x501d66e0b4254de6187443b9cdb744e2752f489e",
      "prizes": {
        "5": [
          605
        ]
      }
    },
    {
      "user": "0xd70804463bb2760c3384fc87bbe779e3d91bab3a",
      "prizes": {
        "4": [
          63
        ],
        "5": [
          157,
          869
        ]
      }
    },
    {
      "user": "0xa8078cabce440b0feadd7264adf179d301fcef18",
      "prizes": {
        "5": [
          706,
          933
        ]
      }
    },
    {
      "user": "0x69d6057698327df512837d46bb55be55f07ba4a2",
      "prizes": {
        "5": [
          81,
          912
        ]
      }
    },
    {
      "user": "0xa7329fd51b2dc832f92a1ec5e05cc35d4d1a095e",
      "prizes": {
        "5": [
          124,
          236,
          360,
          481,
          714,
          831
        ]
      }
    },
    {
      "user": "0xae85bd3136c4da4a29d84e78a8d4b5073ae91c28",
      "prizes": {
        "4": [
          44
        ],
        "5": [
          160
        ]
      }
    },
    {
      "user": "0x9f36a6bb398118bdcd5b1bc3343d8feb6d7d02b9",
      "prizes": {
        "4": [
          163
        ],
        "5": [
          292
        ]
      }
    },
    {
      "user": "0xe24bc6c67fef2ffe40283c1359dce44bd19c72c4",
      "prizes": {
        "5": [
          84
        ]
      }
    },
    {
      "user": "0x718fdf375e1930ba386852e35f5bafc31df3ae66",
      "prizes": {
        "5": [
          660
        ]
      }
    },
    {
      "user": "0xccd72bea12f3927063be3d8798a4b74082713cb5",
      "prizes": {
        "3": [
          41
        ],
        "4": [
          135
        ],
        "5": [
          120,
          156,
          194,
          558,
          613,
          694,
          814,
          984
        ]
      }
    },
    {
      "user": "0xebc52cdfc2fbf28363e59e169a4e471f770a1e62",
      "prizes": {
        "5": [
          657
        ]
      }
    },
    {
      "user": "0x48a7e4f10b34ad5b74eef2ae3f82b69783ec60c4",
      "prizes": {
        "5": [
          100
        ]
      }
    },
    {
      "user": "0xbb9f959f118a5f87875b39f1f866027c5716189d",
      "prizes": {
        "5": [
          301
        ]
      }
    },
    {
      "user": "0xfbcfd0a67bbc544ff547d04d28b8ff1ea4b9d116",
      "prizes": {
        "4": [
          194
        ],
        "5": [
          533
        ]
      }
    },
    {
      "user": "0x6d436d88dc7b6d66b4441781e8d9993bc13c27e3",
      "prizes": {
        "5": [
          340
        ]
      }
    },
    {
      "user": "0x7f25555a0c85b53cb8934960d0e4ae2df65cecab",
      "prizes": {
        "5": [
          466
        ]
      }
    },
    {
      "user": "0x733a53a044346aac1c4bdd64e7f9eddc36c443e1",
      "prizes": {
        "5": [
          35,
          468,
          565
        ]
      }
    },
    {
      "user": "0x5668ead1edb8e2a4d724c8fb9cb5ffeabeb422dc",
      "prizes": {
        "5": [
          648
        ]
      }
    },
    {
      "user": "0xcc22f7f6a8296ed44f0f0e758374675120909177",
      "prizes": {
        "4": [
          66
        ],
        "5": [
          892
        ]
      }
    },
    {
      "user": "0xdadd6e94b6ab894e536b5eb90a2bb04bbd4e78b8",
      "prizes": {
        "5": [
          277
        ]
      }
    },
    {
      "user": "0xb72b643d47b4b7ea6bf1dd12e1a8ad7050f7cbd8",
      "prizes": {
        "5": [
          965
        ]
      }
    },
    {
      "user": "0xb2e5abaa7ccb1228d9a8f63e8442a94f4112bd0b",
      "prizes": {
        "5": [
          209
        ]
      }
    },
    {
      "user": "0x0d3d681762f9eda9541fab6acfb17c50025b630b",
      "prizes": {
        "5": [
          580
        ]
      }
    },
    {
      "user": "0x649c92a98b8c163de6bba53effd55ad2d89553b7",
      "prizes": {
        "5": [
          725
        ]
      }
    },
    {
      "user": "0x1a59e9c02ec869065e301cfcc0ce7835e94ec07f",
      "prizes": {
        "4": [
          136
        ],
        "5": [
          924
        ]
      }
    },
    {
      "user": "0x2f358e304115bb32ec76899965fc5b91a23cabe1",
      "prizes": {
        "5": [
          9
        ]
      }
    },
    {
      "user": "0x7032bebd3b9ea25a6d34bf476d1a569b7043a232",
      "prizes": {
        "4": [
          16
        ]
      }
    },
    {
      "user": "0xe22776140b65f3c56562c26a7f76b0fe6476d6b9",
      "prizes": {
        "4": [
          70
        ]
      }
    },
    {
      "user": "0x7b22fda532f9f9fb688e502d4caf7b2b9bd36a26",
      "prizes": {
        "3": [
          23
        ]
      }
    }
  ],
  "0xa58163334eba40fa6e81a77c2b36f252a945928a": [],
  "0xa74997653ee4c8a60989161c621b042414413111": [],
  "0xb0be8eab1cba26963f382fbc36aaff9e7b89244c": [],
  "0xb4063d1f0b0b7caee88708895ec4e365bf44b984": [],
  "0xb4911efd3d53352f658536afd37e7897cb7dd7f6": [],
  "0xb61bf70e978f7260768c26d8737f6dbd5778360c": [],
  "0xbfadf0d82f891042352f83d0f1bdeddaf1181cf3": [],
  "0xcc3fefb704be360245f8dd0386ac206941e66467": [],
  "0xcf6abb37336e3a756b564e2c29222bf187a0de2a": [],
  "0xd9825b290bab900d84f341ddbf9f96b71bac39b2": [],
  "0xdaaf4b68b1299fb9b05ae578cb3d06c8528138d4": [],
  "0xdeef914a2ee2f2014ce401dcb4e13f6540d20ba7": [],
  "0xe13ee913c132af8c4887a6c037c0da10b6d43d18": [],
  "0xe2778b7c04a44dc8480fee88edc3cef8ee11fce0": [],
  "0xe5f8c4e783839e14080daf3e28d64e3140596989": [],
  "0xed953dcc2e93224a94944bf8fd6420324515e7c4": [],
  "0xefd811808b2366fa07d9dc5f8c64046a421a5e97": [],
  "0xf1d934d5a3c6e530ac1450c92af5ba01eb90d4de": [],
  "0xf80a7327ced2d6aba7246e0de1383ddb57fd4475": [],
  "0xfdd33b8413a69ba9ce140b479f27ee7ab133850e": []
}