{
  "0x216a7d520992ed198593a16e0b17c784c9cdc660": [],
  "0x2af72b1ca996186d3f9842c415a302a8585277f9": [],
  "0x308dee147d98b3c3e6a211337cf96dbdad54e7cc": [],
  "0x65f3aea2594d82024b7ee98ddcf08f991ab1c626": [],
  "0x874169673a5c72867f72ce5ca64c38d96b75d075": [],
  "0xb75af20ecadabed9049cc2f50e38bad2768b35cf": [
    {
      "user": "0xe68967c95f5a9bccfdd711a2cbc23ec958f147ef",
      "prizes": {
        "3": [
          18
        ]
      }
    }
  ],
  "0xbb7e99abccce01589ad464ff698ad139b0705d90": [
    {
      "user": "0x000001ac4e512d670c34fedf6c71ce2f49fb160a",
      "prizes": {
        "2": [
          12
        ],
        "3": [
          30
        ],
        "4": [
          205
        ],
        "5": [
          84,
          87,
          88,
          176,
          345,
          353,
          447,
          488,
          659,
          825
        ]
      }
    },
    {
      "user": "0x08e166bddc849cfd91084e828b5096085e8e0875",
      "prizes": {
        "3": [
          15
        ],
        "4": [
          163
        ],
        "5": [
          84,
          440,
          577,
          682
        ]
      }
    },
    {
      "user": "0x78b6131960f6432b3bc482d81ee49775fe1e5cbd",
      "prizes": {
        "1": [
          3
        ],
        "3": [
          6
        ],
        "4": [
          177
        ],
        "5": [
          254,
          598,
          832
        ]
      }
    },
    {
      "user": "0xb198d4b587650652a365e38263ec69e158c755f1",
      "prizes": {
        "5": [
          806
        ]
      }
    },
    {
      "user": "0x0980b34ade9476dba81bcdb0f865a333793ad1c2",
      "prizes": {
        "4": [
          69,
          93,
          155,
          203
        ],
        "5": [
          42,
          103,
          226,
          314,
          333,
          350,
          370,
          387,
          468,
          510,
          594,
          628,
          631,
          655,
          681,
          805,
          879,
          951,
          962,
          976
        ]
      }
    },
    {
      "user": "0xad78662714cd0042b4c602a8e18d0e4a25cf79d7",
      "prizes": {
        "4": [
          13,
          40,
          48,
          50,
          113,
          211
        ],
        "5": [
          133,
          300,
          308,
          323,
          324,
          409,
          412,
          471,
          566,
          572,
          601,
          618,
          649,
          680,
          726,
          734,
          760,
          767,
          783,
          802,
          813,
          844,
          861,
          866,
          995,
          1010
        ]
      }
    },
    {
      "user": "0x1d5374fa55cd56d35cfe6de668804639185017f2",
      "prizes": {
        "5": [
          213,
          569
        ]
      }
    },
    {
      "user": "0x09229be5011e073165c87b788c8407390c61a43f",
      "prizes": {
        "5": [
          235,
          397,
          410,
          413,
          466,
          827,
          926
        ]
      }
    },
    {
      "user": "0xcd7920b1d9c26e0896e5ca0054609dbb882046b6",
      "prizes": {
        "5": [
          177,
          687
        ]
      }
    },
    {
      "user": "0x376d5c3a16e9d015e8c584bb2d278e25f0ccb27b",
      "prizes": {
        "4": [
          159
        ],
        "5": [
          140,
          158,
          433,
          690
        ]
      }
    },
    {
      "user": "0x8d0734865f984374435d5e9f814a9704fdc51a64",
      "prizes": {
        "2": [
          7
        ],
        "5": [
          215,
          488,
          828
        ]
      }
    },
    {
      "user": "0xd826bd9c9215905a536dd48ebaf54737cabceb76",
      "prizes": {
        "4": [
          71
        ]
      }
    },
    {
      "user": "0x9df87b0cb61e83aa4025b430740d0fdef48c9839",
      "prizes": {
        "4": [
          103
        ]
      }
    },
    {
      "user": "0x99530e4806194af07b42848d110f36bdce1f9723",
      "prizes": {
        "4": [
          72
        ]
      }
    }
  ],
  "0xc9dbcc909f951d9353fc6a24accd65d746dd67c4": []
}