{
  "0x032a345a6975c85cde958810897ae493ee5db396": [],
  "0x119d2bc7bb9b94f5518ce30169457ff358b47535": [],
  "0x1be9123d4e95c109931f234a157d07cf73f033b7": [],
  "0x1e56e11bf011b46546540036dbee8820ddce5cdf": [],
  "0x23cd31beec8980e7f8aeb7e76d45fe3da4de1592": [],
  "0x327b2ea9668a552fe5dec8e3c6e47e540a0a58c6": [
    {
      "user": "0x327b2ea9668a552fe5dec8e3c6e47e540a0a58c6",
      "prizes": {
        "3": [
          3,
          16,
          29,
          36,
          38,
          39,
          46,
          62
        ],
        "4": [
          3,
          6,
          7,
          8,
          9,
          11,
          12,
          13,
          14,
          15,
          19,
          22,
          28,
          29,
          31,
          37,
          40,
          41,
          47,
          49,
          52,
          53,
          57,
          60,
          64,
          68,
          69,
          71,
          79,
          83,
          84,
          92,
          100,
          103,
          113,
          118,
          119,
          121,
          127,
          131,
          132,
          135,
          137,
          140,
          146,
          148,
          155,
          159,
          160,
          163,
          164,
          166,
          167,
          169,
          180,
          185,
          187,
          188,
          189,
          191,
          198,
          201,
          204,
          205,
          206,
          212,
          217,
          218,
          220,
          222,
          223,
          230,
          235,
          238,
          244,
          245,
          247,
          250,
          252,
          253,
          255
        ],
        "5": [
          2,
          5,
          13,
          14,
          22,
          23,
          25,
          27,
          32,
          36,
          42,
          46,
          48,
          49,
          50,
          52,
          58,
          60,
          62,
          65,
          66,
          67,
          69,
          70,
          76,
          78,
          83,
          86,
          92,
          94,
          98,
          99,
          101,
          103,
          104,
          107,
          108,
          111,
          112,
          120,
          122,
          123,
          125,
          126,
          128,
          151,
          155,
          160,
          165,
          166,
          172,
          174,
          176,
          180,
          183,
          185,
          186,
          191,
          199,
          205,
          208,
          209,
          210,
          211,
          213,
          215,
          225,
          228,
          230,
          232,
          233,
          243,
          246,
          255,
          259,
          260,
          262,
          263,
          264,
          265,
          274,
          275,
          276,
          280,
          282,
          283,
          291,
          297,
          302,
          311,
          314,
          315,
          334,
          336,
          344,
          345,
          347,
          348,
          353,
          364,
          365,
          366,
          367,
          372,
          375,
          378,
          379,
          383,
          386,
          388,
          390,
          392,
          394,
          399,
          401,
          402,
          405,
          408,
          414,
          419,
          420,
          426,
          428,
          430,
          431,
          433,
          434,
          435,
          438,
          439,
          441,
          442,
          443,
          446,
          447,
          454,
          464,
          473,
          474,
          477,
          483,
          485,
          486,
          490,
          493,
          508,
          511,
          512,
          517,
          519,
          526,
          529,
          532,
          539,
          540,
          541,
          543,
          548,
          550,
          558,
          559,
          567,
          569,
          574,
          575,
          576,
          583,
          586,
          587,
          588,
          591,
          595,
          598,
          601,
          603,
          606,
          607,
          612,
          615,
          617,
          618,
          619,
          620,
          629,
          631,
          633,
          634,
          635,
          639,
          640,
          643,
          645,
          649,
          662,
          666,
          669,
          670,
          671,
          672,
          680,
          685,
          687,
          695,
          702,
          706,
          710,
          711,
          720,
          721,
          722,
          723,
          727,
          728,
          733,
          734,
          735,
          736,
          737,
          738,
          742,
          743,
          746,
          747,
          750,
          758,
          765,
          769,
          772,
          777,
          779,
          789,
          790,
          793,
          797,
          801,
          808,
          810,
          811,
          812,
          819,
          820,
          824,
          827,
          828,
          830,
          831,
          832,
          833,
          835,
          841,
          844,
          847,
          849,
          855,
          858,
          862,
          866,
          874,
          876,
          877,
          879,
          888,
          890,
          895,
          896,
          898,
          899,
          901,
          902,
          905,
          906,
          910,
          912,
          919,
          920,
          921,
          922,
          924,
          928,
          931,
          932,
          933,
          935,
          945,
          948,
          956,
          959,
          962,
          967,
          968,
          969,
          970,
          971,
          973,
          974,
          977,
          982,
          986,
          991,
          992,
          996,
          997,
          998,
          999,
          1003,
          1004,
          1010,
          1013,
          1017,
          1020,
          1023
        ]
      }
    }
  ],
  "0x32b27d1ab97607bf276ce3c915ef9d66fb35b73c": [],
  "0x4dc1de83149c972050cdd7d5ce9a3f75f70e4d8f": [
    {
      "user": "0x4a3e6e66f8c32bc05a50879f872b1177a1573cdf",
      "prizes": {
        "4": [
          149
        ],
        "5": [
          212
        ]
      }
    }
  ],
  "0x4e42f783db2d0c5bdff40fdc66fcae8b1cda4a43": [
    {
      "user": "0xe6f43a9dc80d833decf722df5d0a2c7e6013ef07",
      "prizes": {
        "4": [
          179
        ],
        "5": [
          665
        ]
      }
    },
    {
      "user": "0x8452f039e833b68ef48fe137d57854fc1c2e3337",
      "prizes": {
        "4": [
          133
        ]
      }
    },
    {
      "user": "0x7073964454043db0b3f820fe5a04d3a7f5c0e392",
      "prizes": {
        "4": [
          119
        ],
        "5": [
          535,
          668,
          893
        ]
      }
    },
    {
      "user": "0xeb85bdfd2b0ab696e576b2345aed3a8bf4d2801e",
      "prizes": {
        "4": [
          40
        ]
      }
    },
    {
      "user": "0x5ee7253fbef24cf4718d60d7b9622ec70f343f8f",
      "prizes": {
        "4": [
          146
        ],
        "5": [
          163,
          209,
          284,
          533,
          794
        ]
      }
    },
    {
      "user": "0xddc2dc94999437c0f1e36ae55e8296b3ba7231de",
      "prizes": {
        "4": [
          222,
          224
        ],
        "5": [
          129,
          202,
          354,
          419,
          888
        ]
      }
    },
    {
      "user": "0x7c6accd51cbbdd53354de581841803b4f79d48e7",
      "prizes": {
        "4": [
          94
        ],
        "5": [
          235,
          940
        ]
      }
    },
    {
      "user": "0x2be58f4be8557756c69bd277bdc29b701f7e75b6",
      "prizes": {
        "5": [
          882
        ]
      }
    },
    {
      "user": "0x771426817d8a829d3798ee07afef8889c4117c3c",
      "prizes": {
        "5": [
          840,
          848,
          978
        ]
      }
    },
    {
      "user": "0x0bda59997765a113bea8ca9cba319b35fb287fc8",
      "prizes": {
        "5": [
          245,
          387,
          646,
          759,
          943
        ]
      }
    },
    {
      "user": "0x3806c0e88f48123201b01414591ca2a8faa27f0a",
      "prizes": {
        "5": [
          271
        ]
      }
    },
    {
      "user": "0x15bbcf76110505d3be5a9eb10c63f57f66d20c40",
      "prizes": {
        "5": [
          280,
          730,
          832
        ]
      }
    },
    {
      "user": "0x1e2f3bd48afbb2209dad23ee7a3aebdd1a066d6b",
      "prizes": {
        "5": [
          556
        ]
      }
    },
    {
      "user": "0x24a3bde2bd95fe4c36894049e34501d340d9fd56",
      "prizes": {
        "5": [
          77,
          894
        ]
      }
    },
    {
      "user": "0x03719ee8f7cee79be9b467bcd82f882de428bcbb",
      "prizes": {
        "5": [
          175,
          803
        ]
      }
    },
    {
      "user": "0x0857d7771aa13a0988f7aac9d72bfeea6b69d73c",
      "prizes": {
        "5": [
          398,
          791
        ]
      }
    },
    {
      "user": "0xa184aa8488908b43ccf43b5ef13ae528693dfd00",
      "prizes": {
        "5": [
          131,
          571
        ]
      }
    }
  ],
  "0x4fd55e86485be48111b0ad17558da666458b01b6": [],
  "0x50b2271c06b528223063ca340c496a0ed6c08714": [],
  "0x52e66d9055235be184c87f1caec81bd2d5fa17ab": [],
  "0x52ee27824a64430cbd1be03794d4eb92e4b8bbd0": [],
  "0x561384ca89a9ab84954027df88b59854ff62a475": [],
  "0x5b623c127254c6fec04b492ecdf4b11c45fbb9d5": [
    {
      "user": "0x9f36a6bb398118bdcd5b1bc3343d8feb6d7d02b9",
      "prizes": {
        "5": [
          82
        ]
      }
    },
    {
      "user": "0xcbdac00f48de6f56f61a058dc63bdd1a8130a5d2",
      "prizes": {
        "5": [
          287
        ]
      }
    },
    {
      "user": "0x03719ee8f7cee79be9b467bcd82f882de428bcbb",
      "prizes": {
        "5": [
          76
        ]
      }
    },
    {
      "user": "0x3548c9e5deda1c2cfa57f3536dc220cfbae46f0c",
      "prizes": {
        "5": [
          69,
          394
        ]
      }
    },
    {
      "user": "0x15bbcf76110505d3be5a9eb10c63f57f66d20c40",
      "prizes": {
        "5": [
          150
        ]
      }
    }
  ],
  "0x5e568e9601b049eda5f3e538ff685e5f30284e38": [],
  "0x6428ddb6ef1818fa99552e10882d34c1db57bbca": [],
  "0x65d7336a4a95c95f6a598cc7a5d6822c69d82ed0": [],
  "0x663dc65f5372dd952149d45fc3dcd0530285fbfe": [],
  "0x6b5a5c55e9dd4bb502ce25bbfbaa49b69cf7e4dd": [
    {
      "user": "0xaf5b16f740bed90af42df6c28e5cd79458c102f1",
      "prizes": {
        "4": [
          44
        ],
        "5": [
          463,
          669
        ]
      }
    },
    {
      "user": "0x3b9123d7b37f72256bb66f155d99789a2781e149",
      "prizes": {
        "4": [
          59,
          157,
          164
        ],
        "5": [
          478
        ]
      }
    },
    {
      "user": "0xda360606e4e484e7c97abbcc8441ae0887f88a18",
      "prizes": {
        "5": [
          820
        ]
      }
    },
    {
      "user": "0x4a3e6e66f8c32bc05a50879f872b1177a1573cdf",
      "prizes": {
        "5": [
          281
        ]
      }
    },
    {
      "user": "0xeb85bdfd2b0ab696e576b2345aed3a8bf4d2801e",
      "prizes": {
        "4": [
          82,
          98,
          111,
          172,
          177,
          214,
          247
        ],
        "5": [
          21,
          68,
          73,
          92,
          121,
          194,
          238,
          242,
          314,
          334,
          336,
          354,
          378,
          439,
          485,
          507,
          544,
          562,
          607,
          715,
          766,
          792,
          816,
          840,
          856,
          961,
          978,
          1004
        ]
      }
    },
    {
      "user": "0xbe4feae32210f682a41e1c41e3eaf4f8204cd29e",
      "prizes": {
        "4": [
          82,
          144,
          161
        ],
        "5": [
          36,
          225,
          482,
          570,
          598,
          678,
          851,
          918,
          957
        ]
      }
    },
    {
      "user": "0xe9945b3acbdc2f9dcad8871f01aa9dabbb20d882",
      "prizes": {
        "5": [
          102,
          259,
          1010
        ]
      }
    },
    {
      "user": "0xcc22f7f6a8296ed44f0f0e758374675120909177",
      "prizes": {
        "4": [
          131,
          237
        ],
        "5": [
          690,
          698,
          729,
          809,
          918
        ]
      }
    },
    {
      "user": "0x6665e62ef6f6db29d5f8191fbac472222c2cc80f",
      "prizes": {
        "5": [
          259,
          734
        ]
      }
    },
    {
      "user": "0x8445271fca0d979aae411f0b72f4ee9a620d41d7",
      "prizes": {
        "5": [
          291,
          396,
          531,
          785,
          830
        ]
      }
    },
    {
      "user": "0x322ffce13679647e5206a09d129aa834567b8993",
      "prizes": {
        "5": [
          516
        ]
      }
    },
    {
      "user": "0x144e1547ad7be53ed5f751406a661540b860d522",
      "prizes": {
        "5": [
          418,
          469,
          483
        ]
      }
    },
    {
      "user": "0xb6aeafd822eada55f7c8bbcae4f4ea81a50a92d7",
      "prizes": {
        "4": [
          151
        ],
        "5": [
          642,
          803,
          939
        ]
      }
    },
    {
      "user": "0x5955037f92e18abb42dee44754615d31190b21bb",
      "prizes": {
        "4": [
          149,
          197,
          224
        ],
        "5": [
          78,
          244,
          572,
          797,
          815,
          873,
          927,
          941
        ]
      }
    },
    {
      "user": "0x0002f08d82d80b69a736416c1666f5a1041c1666",
      "prizes": {
        "4": [
          25
        ],
        "5": [
          555,
          662,
          701
        ]
      }
    },
    {
      "user": "0x4cd7a2a984ced0c9f7316b2b4427601e6db87b30",
      "prizes": {
        "5": [
          304
        ]
      }
    },
    {
      "user": "0x7e50cc9b66ae6175aff7084b041d10f2ff7fe191",
      "prizes": {
        "5": [
          108,
          139,
          144,
          358,
          390,
          475,
          581,
          698,
          811
        ]
      }
    },
    {
      "user": "0xca74b335c5abb4ffde7945c34112917921f4683b",
      "prizes": {
        "5": [
          827
        ]
      }
    },
    {
      "user": "0xff19ad332cc5bb32703a3058c6f93ce177cfbb08",
      "prizes": {
        "4": [
          82
        ],
        "5": [
          27,
          969
        ]
      }
    },
    {
      "user": "0x9545109390123cdf6e55dab797d517f6021dd759",
      "prizes": {
        "5": [
          987
        ]
      }
    },
    {
      "user": "0x8de2483bc7a741aea2a8a15811926ea9943e0529",
      "prizes": {
        "4": [
          41
        ],
        "5": [
          97,
          202,
          301,
          338,
          366,
          896,
          978
        ]
      }
    },
    {
      "user": "0x4673d288d782535ce916e8630bd43fe1e3e9c1d9",
      "prizes": {
        "4": [
          34,
          206
        ],
        "5": [
          293,
          330,
          339,
          414,
          755,
          764,
          799,
          829,
          842,
          895
        ]
      }
    },
    {
      "user": "0xf7f78ddc39357e0c8691991e627fed422e66df1d",
      "prizes": {
        "4": [
          4,
          137,
          143,
          155,
          195,
          237,
          248
        ],
        "5": [
          26,
          58,
          70,
          362,
          390,
          429,
          491,
          528,
          583,
          641,
          649,
          668,
          748,
          785,
          882,
          933,
          1014
        ]
      }
    },
    {
      "user": "0x0857d7771aa13a0988f7aac9d72bfeea6b69d73c",
      "prizes": {
        "4": [
          15,
          108
        ],
        "5": [
          350,
          816
        ]
      }
    },
    {
      "user": "0x988ce671760dfe2e178972f1817f72d4fdfcfb78",
      "prizes": {
        "4": [
          35
        ],
        "5": [
          314,
          339,
          607
        ]
      }
    },
    {
      "user": "0xe13ee4df81868304b4a4ba21ca0da6dc59de48be",
      "prizes": {
        "5": [
          165
        ]
      }
    },
    {
      "user": "0x52f8b09fac8e1b7d7dc45643ca27d0f573814ab8",
      "prizes": {
        "4": [
          34,
          171,
          209
        ],
        "5": [
          45,
          273,
          565,
          597,
          705,
          825,
          949
        ]
      }
    },
    {
      "user": "0xd70804463bb2760c3384fc87bbe779e3d91bab3a",
      "prizes": {
        "4": [
          150,
          237
        ],
        "5": [
          127,
          222,
          360,
          388,
          462,
          545,
          594,
          597,
          683,
          711,
          833,
          926
        ]
      }
    },
    {
      "user": "0x175c4f84f41bd3dc37a42d8260f57bc5475e9753",
      "prizes": {
        "5": [
          444
        ]
      }
    },
    {
      "user": "0x0129663df47117b1990d109b97fb83aab708c6ee",
      "prizes": {
        "4": [
          99
        ],
        "5": [
          930
        ]
      }
    },
    {
      "user": "0xb89729bc7eebbfad2f3dd073ee8f200d1116ae8b",
      "prizes": {
        "5": [
          121,
          799
        ]
      }
    },
    {
      "user": "0x957b022767e8427e08de78ab5445ff006ab41f61",
      "prizes": {
        "5": [
          1015
        ]
      }
    },
    {
      "user": "0xfc49bf8d2607db75ba3a38d1f7b8ef1e4a1b03ec",
      "prizes": {
        "4": [
          78
        ],
        "5": [
          138,
          151,
          763,
          824,
          1013
        ]
      }
    },
    {
      "user": "0xe24bc6c67fef2ffe40283c1359dce44bd19c72c4",
      "prizes": {
        "4": [
          99
        ],
        "5": [
          140,
          455,
          503,
          807,
          855
        ]
      }
    },
    {
      "user": "0x764f4909251f81976a0a2dcebce95333e4c27517",
      "prizes": {
        "4": [
          171
        ],
        "5": [
          28,
          93,
          1010
        ]
      }
    },
    {
      "user": "0x9f36a6bb398118bdcd5b1bc3343d8feb6d7d02b9",
      "prizes": {
        "5": [
          706,
          947
        ]
      }
    },
    {
      "user": "0x714f68453ea8cfcf11463d8ee8bc1922a8732eb1",
      "prizes": {
        "4": [
          3,
          70,
          114
        ],
        "5": [
          40,
          260,
          433,
          572,
          599,
          602,
          785,
          830,
          918
        ]
      }
    },
    {
      "user": "0x1200eb4fa3df9903fc6eff1d7a4a5d17502329b2",
      "prizes": {
        "4": [
          1,
          208
        ],
        "5": [
          113,
          115,
          254,
          695,
          907,
          970,
          975
        ]
      }
    },
    {
      "user": "0x28458788fb965bcac5f0df629916a3735112dac6",
      "prizes": {
        "4": [
          3,
          71,
          77,
          151,
          152,
          213
        ],
        "5": [
          14,
          43,
          109,
          285,
          308,
          406,
          491
        ]
      }
    },
    {
      "user": "0x861f57da59e8c8f2d766abbc35843cbf2880e360",
      "prizes": {
        "5": [
          558,
          765
        ]
      }
    },
    {
      "user": "0x85733c9aec50f084ac58259ec23933931cbbc2ee",
      "prizes": {
        "4": [
          64,
          247
        ],
        "5": [
          170,
          226,
          427
        ]
      }
    },
    {
      "user": "0xa8078cabce440b0feadd7264adf179d301fcef18",
      "prizes": {
        "4": [
          200
        ],
        "5": [
          937
        ]
      }
    },
    {
      "user": "0x58bbb8d3c0c16b35c6d09a8306dd012b61911699",
      "prizes": {
        "5": [
          53,
          540
        ]
      }
    },
    {
      "user": "0xf80a7327ced2d6aba7246e0de1383ddb57fd4475",
      "prizes": {
        "4": [
          68
        ]
      }
    },
    {
      "user": "0x94096aa1bc52fe6351ad72318ec0e85edbd7b4de",
      "prizes": {
        "4": [
          199
        ]
      }
    },
    {
      "user": "0xbaf9b2027a92fa2f851cc0df405251bbc80f10c8",
      "prizes": {
        "4": [
          88
        ]
      }
    },
    {
      "user": "0xa2c260f0fcefafba6477f32809efdf884008765a",
      "prizes": {
        "4": [
          137
        ]
      }
    }
  ],
  "0x6bb041d7e70b7040611ef688b5e707a799ade60a": [],
  "0x75d700f4c21528a2bb603b6ed899acfde5c4b086": [
    {
      "user": "0x3216a8a03b07b6b19cbc21d62c8942e625fc3e07",
      "prizes": {
        "5": [
          673
        ]
      }
    },
    {
      "user": "0x5c59fff579e94e3ef2deeb66d031c984b4d6b7f4",
      "prizes": {
        "4": [
          45
        ]
      }
    }
  ],
  "0x76a4929d42d51184fd05240857a741e44e515087": [],
  "0x78adc13c9ab327c79d10cab513b7c6bd3b346858": [
    {
      "user": "0xa426bfdda22814a691fabcb44dcbe696b0fd16d8",
      "prizes": {
        "4": [
          39,
          73
        ],
        "5": [
          37,
          175,
          290,
          441,
          786,
          886
        ]
      }
    },
    {
      "user": "0x370d508696a9ca657eb49ca991f4184e955b4487",
      "prizes": {
        "4": [
          135,
          199
        ],
        "5": [
          39,
          41,
          107,
          134,
          154,
          169,
          363,
          399,
          424,
          454,
          533,
          568,
          574,
          594,
          636,
          764,
          786,
          841,
          878,
          984,
          988,
          1013
        ]
      }
    },
    {
      "user": "0xa8078cabce440b0feadd7264adf179d301fcef18",
      "prizes": {
        "5": [
          110
        ]
      }
    },
    {
      "user": "0x589eb925ee2999b82b6c6dfa800a7da79de42376",
      "prizes": {
        "4": [
          10
        ],
        "5": [
          452
        ]
      }
    },
    {
      "user": "0xa715c8b17268f140d76494c12ec07b48218549c4",
      "prizes": {
        "5": [
          117
        ]
      }
    },
    {
      "user": "0x9419ba813f206e8b389944d3a292f22ce56c36dd",
      "prizes": {
        "5": [
          271,
          296,
          680,
          832,
          902,
          981
        ]
      }
    },
    {
      "user": "0x3bc1158e5bce8c10e5da0edfbb94b261eec46a76",
      "prizes": {
        "5": [
          336,
          396,
          477
        ]
      }
    },
    {
      "user": "0x175c4f84f41bd3dc37a42d8260f57bc5475e9753",
      "prizes": {
        "5": [
          269
        ]
      }
    },
    {
      "user": "0x9342e2ac6dd4a907948e91e80d2734ecac1d70ec",
      "prizes": {
        "5": [
          74
        ]
      }
    },
    {
      "user": "0x797bc498edee4357a16a1054db0323cbd04c84c3",
      "prizes": {
        "5": [
          103
        ]
      }
    }
  ],
  "0x7f5c2b379b88499ac2b997db583f8079503f25b9": [
    {
      "user": "0x0d3d681762f9eda9541fab6acfb17c50025b630b",
      "prizes": {
        "4": [
          232
        ],
        "5": [
          225,
          735,
          781
        ]
      }
    },
    {
      "user": "0xf199f2c9db81d8359c9eaed16d7df8a1857d3fc3",
      "prizes": {
        "5": [
          609
        ]
      }
    },
    {
      "user": "0x9b2247e137387c2a2c49e9607e4b70473891e9fc",
      "prizes": {
        "4": [
          231
        ],
        "5": [
          738
        ]
      }
    },
    {
      "user": "0xd095e0f8c72e22319846b643c4bac0cac1f67006",
      "prizes": {
        "5": [
          413,
          638
        ]
      }
    },
    {
      "user": "0x5ee7253fbef24cf4718d60d7b9622ec70f343f8f",
      "prizes": {
        "5": [
          67,
          226,
          829,
          869,
          969
        ]
      }
    },
    {
      "user": "0xa5c3a513645a9a00cb561fed40438e9dfe0d6a69",
      "prizes": {
        "4": [
          131
        ],
        "5": [
          259,
          297,
          876
        ]
      }
    },
    {
      "user": "0xf8445b5ee5167c5d5ab91e29dc542851295f9b17",
      "prizes": {
        "4": [
          1,
          13,
          15,
          27,
          202,
          214,
          224,
          233,
          241
        ],
        "5": [
          1,
          69,
          122,
          127,
          132,
          167,
          244,
          249,
          255,
          261,
          268,
          284,
          298,
          301,
          302,
          334,
          386,
          387,
          401,
          403,
          404,
          408,
          483,
          515,
          531,
          549,
          572,
          598,
          602,
          618,
          627,
          752,
          757,
          762,
          778,
          805,
          881,
          894,
          962,
          1006,
          1018
        ]
      }
    },
    {
      "user": "0x175c4f84f41bd3dc37a42d8260f57bc5475e9753",
      "prizes": {
        "5": [
          6,
          281,
          456,
          740,
          772,
          777,
          904
        ]
      }
    },
    {
      "user": "0xe2d31a02163d2a49aebd19aefcd43b9119700fcf",
      "prizes": {
        "4": [
          44,
          105,
          158
        ],
        "5": [
          171,
          426
        ]
      }
    },
    {
      "user": "0x58bbb8d3c0c16b35c6d09a8306dd012b61911699",
      "prizes": {
        "4": [
          69,
          70,
          164,
          229
        ],
        "5": [
          12,
          34,
          49,
          81,
          145,
          159,
          192,
          194,
          205,
          289,
          296,
          304,
          331,
          347,
          350,
          361,
          413,
          420,
          460,
          505,
          511,
          548,
          635,
          643,
          769,
          778,
          784,
          823,
          876,
          913,
          959,
          975,
          1005
        ]
      }
    },
    {
      "user": "0xa426bfdda22814a691fabcb44dcbe696b0fd16d8",
      "prizes": {
        "4": [
          81,
          132,
          234
        ],
        "5": [
          20,
          22,
          57,
          67,
          135,
          215,
          222,
          306,
          417,
          458,
          676,
          697,
          935,
          959,
          978
        ]
      }
    },
    {
      "user": "0xdd45ca901067d65860b54d4310e37371cd92fb09",
      "prizes": {
        "5": [
          476
        ]
      }
    },
    {
      "user": "0x1f335c8ab8514920dba51a72f39e92b514cbacef",
      "prizes": {
        "5": [
          833
        ]
      }
    },
    {
      "user": "0xeb00afd18bef7634136173002e33491fd41c1e1a",
      "prizes": {
        "5": [
          112
        ]
      }
    },
    {
      "user": "0xff19ad332cc5bb32703a3058c6f93ce177cfbb08",
      "prizes": {
        "5": [
          403
        ]
      }
    },
    {
      "user": "0x6cf2707a5b0156fb8084eff8231775ca279fc81f",
      "prizes": {
        "5": [
          102
        ]
      }
    },
    {
      "user": "0x0501f97dd89a7eec0f8646e39a0b9d0bd608cf31",
      "prizes": {
        "5": [
          143
        ]
      }
    },
    {
      "user": "0x8aeb24ba4a9f25ead8609ee3bc6f52ac8d49ad3b",
      "prizes": {
        "5": [
          467
        ]
      }
    },
    {
      "user": "0xeb85bdfd2b0ab696e576b2345aed3a8bf4d2801e",
      "prizes": {
        "4": [
          95,
          113,
          121,
          122,
          128,
          147,
          154,
          158,
          214,
          221
        ],
        "5": [
          37,
          52,
          84,
          168,
          169,
          263,
          328,
          348,
          401,
          408,
          428,
          438,
          503,
          529,
          554,
          588,
          629,
          643,
          680,
          692,
          715,
          734,
          748,
          782,
          783,
          824,
          895,
          928,
          949,
          1004
        ]
      }
    },
    {
      "user": "0xf8549c9299ccd83e69fdb254e74197286623e13b",
      "prizes": {
        "5": [
          358
        ]
      }
    },
    {
      "user": "0xeae579b24fbd7a36f0a317dfee29f9a35c1b5c1e",
      "prizes": {
        "5": [
          321,
          568
        ]
      }
    },
    {
      "user": "0xf084db3c7a47ccc3b5929e66b977cbc0bca391d2",
      "prizes": {
        "5": [
          185
        ]
      }
    },
    {
      "user": "0xa8078cabce440b0feadd7264adf179d301fcef18",
      "prizes": {
        "5": [
          402,
          421
        ]
      }
    },
    {
      "user": "0x62ee13473eb1f771c3788f70ea988499a6008881",
      "prizes": {
        "5": [
          326,
          956
        ]
      }
    },
    {
      "user": "0xbe8e96c85181c93c1b69d0a09e160b6115318d38",
      "prizes": {
        "5": [
          139,
          568
        ]
      }
    },
    {
      "user": "0xbca99f02221878dd9b7795e50da6a12f0a5180a3",
      "prizes": {
        "4": [
          99,
          246
        ],
        "5": [
          44,
          231,
          355,
          397,
          414,
          490,
          519,
          597,
          613,
          732,
          784,
          854,
          891,
          926,
          940,
          997,
          1012
        ]
      }
    },
    {
      "user": "0xe4defc7e4d0ad002257f678150d0837b182efaba",
      "prizes": {
        "5": [
          305
        ]
      }
    },
    {
      "user": "0xfd9b742d4f971f716ae84d713d0dd120d5318441",
      "prizes": {
        "5": [
          848
        ]
      }
    },
    {
      "user": "0x56f6bf6b793713c050fd02147a45b563bb4d8efa",
      "prizes": {
        "5": [
          148
        ]
      }
    },
    {
      "user": "0x735950b0bebdc7c97658a2fe6b233e944cc352f9",
      "prizes": {
        "5": [
          233,
          297,
          312,
          314,
          840
        ]
      }
    },
    {
      "user": "0xca590551c68a1a67d54770efe8d89c0276df956f",
      "prizes": {
        "5": [
          899
        ]
      }
    },
    {
      "user": "0xa2c260f0fcefafba6477f32809efdf884008765a",
      "prizes": {
        "5": [
          766,
          897,
          929
        ]
      }
    },
    {
      "user": "0xc571b0a45905bb7f3e3b59e81b3d9d22f279a584",
      "prizes": {
        "4": [
          222
        ],
        "5": [
          119,
          172,
          177,
          224,
          242,
          410,
          440,
          486,
          506,
          550,
          593,
          598,
          664,
          686,
          892,
          931,
          942,
          943
        ]
      }
    },
    {
      "user": "0xbe92d5ee826c4458c60a40f52d5ca8b5d52af109",
      "prizes": {
        "4": [
          135,
          140
        ],
        "5": [
          992,
          1000
        ]
      }
    },
    {
      "user": "0x7a9208a793c538f3c131b06847f7fe1c8854f4d0",
      "prizes": {
        "5": [
          400,
          706
        ]
      }
    },
    {
      "user": "0x9b5a53e376eddf11b7015680e1f07372f9fc12c4",
      "prizes": {
        "4": [
          25,
          32,
          97,
          108,
          148,
          155,
          157,
          168,
          203,
          228,
          244
        ],
        "5": [
          16,
          60,
          63,
          64,
          86,
          87,
          94,
          160,
          208,
          250,
          268,
          303,
          323,
          367,
          424,
          429,
          481,
          502,
          504,
          508,
          515,
          518,
          528,
          533,
          540,
          567,
          585,
          630,
          671,
          711,
          720,
          739,
          744,
          780,
          891,
          912,
          913,
          1010,
          1011,
          1017
        ]
      }
    },
    {
      "user": "0x9d32f1e7c5ff707e92b4b30937a1e5e2c2de2462",
      "prizes": {
        "4": [
          205
        ],
        "5": [
          279,
          675
        ]
      }
    },
    {
      "user": "0x4ae5ec9f4e0d3a104b2361e75abb5dbf9834fa1a",
      "prizes": {
        "4": [
          184
        ],
        "5": [
          250
        ]
      }
    },
    {
      "user": "0xda360606e4e484e7c97abbcc8441ae0887f88a18",
      "prizes": {
        "4": [
          48,
          117,
          134,
          250
        ],
        "5": [
          55,
          140,
          161,
          162,
          271,
          327,
          600,
          793,
          864,
          878,
          923,
          998
        ]
      }
    },
    {
      "user": "0x1d2c052d4a0273de4bf5ba133ad230c25e84e979",
      "prizes": {
        "4": [
          112
        ],
        "5": [
          102,
          665,
          824,
          863
        ]
      }
    },
    {
      "user": "0x7c6accd51cbbdd53354de581841803b4f79d48e7",
      "prizes": {
        "4": [
          1,
          114,
          148,
          216,
          237
        ],
        "5": [
          37,
          47,
          64,
          69,
          129,
          207,
          345,
          347,
          388,
          452,
          465,
          480,
          517,
          588,
          611,
          724,
          791,
          799,
          879,
          990
        ]
      }
    },
    {
      "user": "0xe000802f5005ed958793e7f0520a766f583b70ab",
      "prizes": {
        "5": [
          766
        ]
      }
    },
    {
      "user": "0x3216a8a03b07b6b19cbc21d62c8942e625fc3e07",
      "prizes": {
        "5": [
          102,
          225,
          544,
          580,
          734,
          846,
          1023
        ]
      }
    },
    {
      "user": "0xa9f4b3d3c3e178358cbd7769c907ec123bbad829",
      "prizes": {
        "4": [
          172
        ]
      }
    },
    {
      "user": "0x57a482ea32c7f75a9c0734206f5bd4f9bcb38e12",
      "prizes": {
        "4": [
          129
        ]
      }
    },
    {
      "user": "0x8fd8225483b28618f01d46bdc4d033af69018a5a",
      "prizes": {
        "4": [
          54
        ]
      }
    },
    {
      "user": "0x4673d288d782535ce916e8630bd43fe1e3e9c1d9",
      "prizes": {
        "4": [
          133,
          226
        ]
      }
    },
    {
      "user": "0xb485837605d2e4faba1fb8e978f150c18cdc7489",
      "prizes": {
        "4": [
          145
        ]
      }
    },
    {
      "user": "0x7928a66320e3799a935a877a70eb8567b7c17a75",
      "prizes": {
        "4": [
          91
        ]
      }
    },
    {
      "user": "0x2d4dbb65bfeb78bf33db8381b381f7e909a395be",
      "prizes": {
        "4": [
          96
        ]
      }
    }
  ],
  "0x813c1fa57ce3f5e8d622925f6062b34fe89e24b5": [],
  "0x850ec48d2605aad9c3de345a6a357a9a14b8cf1b": [
    {
      "user": "0xe0e7b7c5ae92fe94d2ae677d81214d6ad7a11c27",
      "prizes": {
        "4": [
          126,
          138,
          192,
          221,
          231
        ],
        "5": [
          108,
          202,
          251,
          262,
          301,
          377,
          416,
          433,
          522,
          536,
          640,
          656,
          720,
          841,
          915,
          970,
          972,
          988,
          993
        ]
      }
    }
  ],
  "0x88f35608aab1e798d0734accefbfe88bf24888eb": [],
  "0x89e25e57e9f24748710b31afd39aa06588c65ab0": [],
  "0x8d1322cabe5ef2949f6bf4941cc7765187c1091a": [
    {
      "user": "0xa0a752b837c5171fe9c065251fcc2d6fcfd730e4",
      "prizes": {
        "4": [
          26,
          40,
          46,
          68,
          79,
          102
        ],
        "5": [
          7,
          128,
          137,
          155,
          219,
          224,
          350,
          482,
          507,
          509,
          611,
          851,
          918,
          920,
          938
        ]
      }
    },
    {
      "user": "0xca590551c68a1a67d54770efe8d89c0276df956f",
      "prizes": {
        "5": [
          357
        ]
      }
    },
    {
      "user": "0x8719560cac241853e89599f6e09a97746539c6e7",
      "prizes": {
        "5": [
          436,
          912
        ]
      }
    },
    {
      "user": "0x0129663df47117b1990d109b97fb83aab708c6ee",
      "prizes": {
        "5": [
          246,
          434
        ]
      }
    },
    {
      "user": "0xa7f92620b0bbdd6d032e24d29cd5bc8337eeb2a6",
      "prizes": {
        "5": [
          2
        ]
      }
    },
    {
      "user": "0xa2ecf324f0db9b049c747b80800643b989f89966",
      "prizes": {
        "5": [
          547
        ]
      }
    }
  ],
  "0x93697c160e5e20ebe7f1f68932fa8e10e00a3c45": [],
  "0x985c54cdf07703b07f303a3039459d6b1dd7330a": [],
  "0xa0be8ac4a90e080138c8c7b1da7bfeb7c3abbc1b": [],
  "0xa99ec0a1018bf964931c7dc421a5de8bca0e32f1": [
    {
      "user": "0xa5c3a513645a9a00cb561fed40438e9dfe0d6a69",
      "prizes": {
        "4": [
          102,
          224
        ],
        "5": [
          126,
          557,
          745,
          837,
          872,
          898,
          935,
          969
        ]
      }
    },
    {
      "user": "0xa45f4e1f3f61587930ebbb769b5c4e64e650416f",
      "prizes": {
        "4": [
          89
        ],
        "5": [
          225
        ]
      }
    }
  ],
  "0xaf2b22b7155da01230d72289dcecb7c41a5a4bd8": [
    {
      "user": "0xbe4feae32210f682a41e1c41e3eaf4f8204cd29e",
      "prizes": {
        "5": [
          776
        ]
      }
    }
  ],
  "0xb9fa079c6f78bda8df61952679161d41f7d8f833": [],
  "0xcadeacae6976bee87ec5ba44b0a5608a2259c517": [],
  "0xe4bce17e4e2d582561f4b2047d5623c3bc529d06": [],
  "0xea57163af350fad87b2ff556c1abf57a87e554a3": []
}