{
  "0x03d3ce84279cb6f54f5e6074ff0f8319d830dafe": [
    {
      "user": "0x174976a7bae6bf9abb80a7bd6896a78fbd17386d",
      "prizes": {
        "3": [
          49
        ],
        "4": [
          44,
          51,
          91,
          92,
          122,
          164,
          220,
          225
        ],
        "5": [
          27,
          44,
          46,
          63,
          64,
          84,
          160,
          227,
          233,
          264,
          283,
          294,
          347,
          370,
          378,
          383,
          424,
          427,
          466,
          477,
          515,
          527,
          544,
          663,
          676,
          702,
          704,
          745,
          757,
          771,
          784,
          818,
          833,
          869,
          885,
          988,
          997,
          1018
        ]
      }
    },
    {
      "user": "0x0d3d681762f9eda9541fab6acfb17c50025b630b",
      "prizes": {
        "3": [
          27
        ],
        "4": [
          220
        ],
        "5": [
          230,
          410,
          682,
          788
        ]
      }
    },
    {
      "user": "0xd914fadffcf805292d74221852e0debfebc682d7",
      "prizes": {
        "3": [
          21
        ],
        "4": [
          185
        ],
        "5": [
          590,
          774,
          781,
          827,
          833,
          905
        ]
      }
    },
    {
      "user": "0x22040d869370ef386d2b52497ead9316947c6062",
      "prizes": {
        "4": [
          9,
          82
        ],
        "5": [
          578,
          942
        ]
      }
    },
    {
      "user": "0x3350692c81dd3a8dbeb46fd3042908ffd0c3e60c",
      "prizes": {
        "4": [
          85
        ]
      }
    },
    {
      "user": "0x1035777a4fab2980d20248d1e4303321d139b021",
      "prizes": {
        "4": [
          73,
          196,
          247
        ],
        "5": [
          674,
          847
        ]
      }
    },
    {
      "user": "0xd9e1bf544ae98c663e108b6c9e0037fd96055b5f",
      "prizes": {
        "4": [
          27,
          224
        ],
        "5": [
          10,
          347,
          383,
          482,
          488,
          660,
          681,
          730,
          893
        ]
      }
    },
    {
      "user": "0xb57e0e66b695662cd8743659351abf859164dda3",
      "prizes": {
        "4": [
          13
        ]
      }
    },
    {
      "user": "0x6622ba5b4fec399b88d4bdcab09936491ea3781a",
      "prizes": {
        "4": [
          2,
          68,
          172,
          240,
          246
        ],
        "5": [
          12,
          26,
          79,
          140,
          142,
          241,
          254,
          442,
          457,
          467,
          494,
          626,
          752,
          769,
          818,
          919,
          1008
        ]
      }
    },
    {
      "user": "0xe48dd2a322a7ebfdaa9680fd2e8cec27cbb7a765",
      "prizes": {
        "4": [
          92,
          96,
          183
        ],
        "5": [
          73,
          88,
          256,
          402,
          617,
          635,
          686,
          835,
          858,
          872
        ]
      }
    },
    {
      "user": "0x63f59dfe5a12be4ecab6ad0ecca568531077af42",
      "prizes": {
        "4": [
          19
        ]
      }
    },
    {
      "user": "0x91b34e88d44fb4c15a5faa04005a48fd5f5e7eea",
      "prizes": {
        "4": [
          22
        ],
        "5": [
          922
        ]
      }
    },
    {
      "user": "0xc0005f8bd45349cc5d7c23ae4371231d3035b3da",
      "prizes": {
        "4": [
          126,
          254
        ]
      }
    },
    {
      "user": "0x4f5755b3e27a7206564e9cf3578efff6e76c3531",
      "prizes": {
        "4": [
          5,
          8,
          26,
          39,
          41,
          52,
          78,
          85,
          125,
          127,
          142,
          144,
          146,
          150,
          160,
          196,
          212,
          228,
          249,
          251
        ],
        "5": [
          5,
          27,
          51,
          65,
          81,
          88,
          116,
          119,
          121,
          161,
          175,
          190,
          199,
          202,
          205,
          275,
          294,
          309,
          313,
          333,
          353,
          363,
          369,
          412,
          420,
          435,
          438,
          441,
          444,
          445,
          475,
          489,
          492,
          494,
          498,
          507,
          522,
          538,
          553,
          567,
          577,
          593,
          602,
          611,
          616,
          617,
          627,
          645,
          646,
          659,
          675,
          678,
          694,
          709,
          714,
          719,
          745,
          768,
          810,
          811,
          813,
          819,
          820,
          822,
          830,
          846,
          849,
          862,
          875,
          877,
          927,
          928,
          938,
          946,
          962,
          969,
          977,
          1019
        ]
      }
    },
    {
      "user": "0xdb53fd872368c4d72ebb814b1e5d7b1babe2b834",
      "prizes": {
        "4": [
          91
        ],
        "5": [
          176,
          707,
          732,
          747,
          926
        ]
      }
    },
    {
      "user": "0x624f6964ecb9f9ccb6b3d5d33640a3440276b305",
      "prizes": {
        "4": [
          45
        ],
        "5": [
          543
        ]
      }
    },
    {
      "user": "0xe80387da5598816213d5ee5b04b4aeea6c63123e",
      "prizes": {
        "4": [
          240
        ],
        "5": [
          911
        ]
      }
    },
    {
      "user": "0x2e1db2e75e05a7137b9386d0cecebea8a92187b5",
      "prizes": {
        "4": [
          144
        ],
        "5": [
          3,
          59,
          425,
          509,
          539,
          644,
          687,
          924
        ]
      }
    },
    {
      "user": "0xb5c305ce16f49c551e5b64f75e8150b62e629026",
      "prizes": {
        "4": [
          5,
          47,
          133,
          223,
          235
        ],
        "5": [
          17,
          67,
          98,
          106,
          111,
          163,
          182,
          249,
          485,
          573,
          591,
          731,
          765,
          815,
          839,
          909,
          980
        ]
      }
    },
    {
      "user": "0x2686544ed0149b134b27009958788cdf4ca8c064",
      "prizes": {
        "4": [
          82,
          106,
          112,
          172,
          227,
          233,
          243
        ],
        "5": [
          14,
          43,
          69,
          259,
          333,
          543,
          559,
          568,
          589,
          676,
          781,
          1004,
          1010
        ]
      }
    },
    {
      "user": "0x376d5c3a16e9d015e8c584bb2d278e25f0ccb27b",
      "prizes": {
        "4": [
          59,
          205
        ],
        "5": [
          18,
          33,
          72,
          90,
          125,
          139,
          393,
          423,
          443,
          450,
          520,
          620,
          625,
          629,
          699,
          718,
          847,
          868,
          877,
          926
        ]
      }
    },
    {
      "user": "0xfeeb4ed5029fa0febe1dbc87fe20ba1118dca49b",
      "prizes": {
        "4": [
          100
        ],
        "5": [
          90,
          141,
          214,
          318,
          324,
          372,
          429
        ]
      }
    },
    {
      "user": "0xf72d29fdb52fccb8d5b7607f92b14c133578587d",
      "prizes": {
        "4": [
          97
        ]
      }
    },
    {
      "user": "0xce451698b148a74b43d2f038488bda5a319d3d29",
      "prizes": {
        "4": [
          3,
          20,
          30,
          33,
          39,
          53,
          65,
          134,
          146,
          176,
          192
        ],
        "5": [
          35,
          52,
          64,
          108,
          114,
          118,
          129,
          147,
          204,
          223,
          291,
          305,
          332,
          337,
          342,
          349,
          364,
          383,
          387,
          398,
          429,
          463,
          478,
          506,
          528,
          530,
          611,
          634,
          652,
          655,
          662,
          727,
          728,
          730,
          739,
          788,
          790,
          829,
          840,
          853,
          944,
          968,
          1012
        ]
      }
    },
    {
      "user": "0x3c1b7fb5d708ee1dc91f199fd9c2d8f3dba6c41d",
      "prizes": {
        "4": [
          7,
          40,
          47,
          75,
          115,
          116,
          140,
          155,
          163,
          169,
          171,
          210,
          211,
          243,
          246,
          249
        ],
        "5": [
          9,
          38,
          41,
          73,
          97,
          150,
          164,
          174,
          234,
          323,
          324,
          336,
          338,
          341,
          348,
          350,
          357,
          373,
          378,
          403,
          416,
          433,
          435,
          453,
          489,
          491,
          530,
          558,
          565,
          566,
          586,
          602,
          624,
          635,
          640,
          646,
          718,
          759,
          772,
          784,
          825,
          837,
          907,
          945,
          949,
          956,
          986,
          987,
          1001,
          1020,
          1021
        ]
      }
    },
    {
      "user": "0x4547f0133001991cbf7c4055a7bec5bae57331e4",
      "prizes": {
        "4": [
          249
        ],
        "5": [
          189,
          697,
          870
        ]
      }
    },
    {
      "user": "0x417372e4d116b6af9e6fbd0d1d16f1483f52f6e8",
      "prizes": {
        "4": [
          73,
          84
        ]
      }
    },
    {
      "user": "0xaa8a19d6bf655bfa3c448248ad2482d05bab6f98",
      "prizes": {
        "4": [
          31
        ],
        "5": [
          198
        ]
      }
    },
    {
      "user": "0x6ce6986ff28bfed84a911682cdb127becb9fc88a",
      "prizes": {
        "4": [
          90,
          152
        ],
        "5": [
          53,
          60,
          165,
          283,
          402,
          433,
          484,
          715,
          772,
          819,
          966,
          990
        ]
      }
    },
    {
      "user": "0x4e42bd9e46444146c6ae31bc301f0ab7cf623ee7",
      "prizes": {
        "4": [
          45
        ],
        "5": [
          961
        ]
      }
    },
    {
      "user": "0xa096f7d0aa83df9e41669629caf4ed435fe228e9",
      "prizes": {
        "4": [
          217
        ],
        "5": [
          392,
          961
        ]
      }
    },
    {
      "user": "0xacfdff61776531f64dbe50ad196f95a1cf92a8d5",
      "prizes": {
        "4": [
          47
        ],
        "5": [
          31,
          797
        ]
      }
    },
    {
      "user": "0x2cdce14d479a2d0aa40e974553dd3ecb65a77b05",
      "prizes": {
        "4": [
          20,
          106,
          112,
          212
        ],
        "5": [
          380,
          875
        ]
      }
    },
    {
      "user": "0xf7467feb2c0b271dfffcdb9c928f0bf546575a87",
      "prizes": {
        "4": [
          0,
          4,
          22,
          30,
          33,
          47,
          52,
          80,
          93,
          103,
          146,
          147,
          160,
          165,
          177,
          182,
          191,
          222,
          241,
          243
        ],
        "5": [
          177,
          185,
          190,
          220,
          236,
          241,
          248,
          249,
          258,
          269,
          294,
          295,
          306,
          336,
          348,
          355,
          434,
          441,
          445,
          462,
          496,
          502,
          557,
          565,
          580,
          585,
          607,
          625,
          626,
          639,
          656,
          687,
          693,
          697,
          710,
          731,
          740,
          751,
          771,
          827,
          834,
          836,
          874,
          932,
          966,
          979,
          983,
          986,
          996,
          1002,
          1017
        ]
      }
    },
    {
      "user": "0x9f36a6bb398118bdcd5b1bc3343d8feb6d7d02b9",
      "prizes": {
        "4": [
          241
        ],
        "5": [
          353
        ]
      }
    },
    {
      "user": "0x9e366e32b067a15a359c2c63f961ac8405cb8e2f",
      "prizes": {
        "4": [
          32
        ]
      }
    },
    {
      "user": "0xafa4d9b35ff0b4dc94d5f17b6dac3017df6f1a5c",
      "prizes": {
        "4": [
          194
        ],
        "5": [
          176,
          189,
          344,
          423,
          433,
          690,
          693,
          797,
          878
        ]
      }
    },
    {
      "user": "0x7b22fda532f9f9fb688e502d4caf7b2b9bd36a26",
      "prizes": {
        "4": [
          29,
          49,
          105,
          109,
          119,
          128,
          142,
          146,
          167,
          205,
          219,
          235,
          244
        ],
        "5": [
          12,
          156,
          224,
          239,
          259,
          264,
          303,
          332,
          333,
          394,
          444,
          511,
          518,
          526,
          598,
          605,
          606,
          610,
          611,
          633,
          711,
          716,
          719,
          773,
          783,
          815,
          871,
          898,
          908,
          955
        ]
      }
    },
    {
      "user": "0x3f2bf7901c71dca7268dbac9c6cb9a4c7265aab6",
      "prizes": {
        "4": [
          233
        ],
        "5": [
          503
        ]
      }
    },
    {
      "user": "0x1713e003c129b39d594b2857e6b1d9bae33d6770",
      "prizes": {
        "4": [
          97
        ],
        "5": [
          668,
          739
        ]
      }
    },
    {
      "user": "0xa9f8275ec69918e26e936be48c1418fe533d0a5a",
      "prizes": {
        "4": [
          0,
          22,
          24,
          63,
          93,
          96,
          107,
          111,
          119,
          137,
          160,
          169,
          170,
          178,
          181,
          183,
          219,
          225,
          229,
          233,
          244,
          255
        ],
        "5": [
          30,
          51,
          57,
          59,
          101,
          118,
          154,
          156,
          162,
          174,
          216,
          222,
          245,
          246,
          272,
          297,
          321,
          335,
          345,
          362,
          375,
          417,
          433,
          443,
          460,
          477,
          481,
          502,
          509,
          517,
          522,
          561,
          582,
          603,
          618,
          630,
          650,
          662,
          672,
          722,
          727,
          728,
          737,
          779,
          792,
          806,
          846,
          855,
          862,
          867,
          877,
          881,
          887,
          891,
          901,
          920,
          934,
          938,
          939,
          944,
          947,
          970,
          981,
          990
        ]
      }
    },
    {
      "user": "0xd9d5b78c3126859877ff7eb1011c6cc67a05b2d7",
      "prizes": {
        "4": [
          98
        ],
        "5": [
          117
        ]
      }
    },
    {
      "user": "0x8e49d2574042611cf30551e90d37d7b2c08b7028",
      "prizes": {
        "4": [
          11,
          49,
          53,
          56,
          79,
          107,
          114,
          136,
          221,
          243,
          245
        ],
        "5": [
          11,
          12,
          65,
          88,
          110,
          122,
          167,
          173,
          179,
          184,
          199,
          219,
          222,
          228,
          238,
          287,
          289,
          294,
          304,
          309,
          371,
          396,
          407,
          411,
          437,
          472,
          483,
          492,
          509,
          535,
          596,
          599,
          600,
          605,
          633,
          683,
          702,
          716,
          761,
          765,
          786,
          787,
          796,
          798,
          870,
          891,
          901,
          914,
          945,
          957,
          961,
          966,
          969,
          974,
          988,
          1016
        ]
      }
    },
    {
      "user": "0xd8adba33d0059d8978087a6ef68690d80add0b29",
      "prizes": {
        "5": [
          591
        ]
      }
    },
    {
      "user": "0xc98931d718992da33373b80665e95485605a5197",
      "prizes": {
        "5": [
          698
        ]
      }
    },
    {
      "user": "0x9342e2ac6dd4a907948e91e80d2734ecac1d70ec",
      "prizes": {
        "5": [
          720,
          738,
          887
        ]
      }
    },
    {
      "user": "0x280e4df73c589623eed589d94193a56dab46ba42",
      "prizes": {
        "5": [
          215
        ]
      }
    },
    {
      "user": "0x717f7f77458886fe97acd31f5ee7f175abf78582",
      "prizes": {
        "5": [
          988
        ]
      }
    },
    {
      "user": "0xa8033118b5393bceda847e62eb69a03188cb4a89",
      "prizes": {
        "5": [
          75,
          349
        ]
      }
    },
    {
      "user": "0xb367782bbc3376dae3b89669cc89c9de200e70e2",
      "prizes": {
        "5": [
          374
        ]
      }
    },
    {
      "user": "0x0de4b96c9be779034397db6d339c5f92d5449662",
      "prizes": {
        "5": [
          69,
          565
        ]
      }
    },
    {
      "user": "0x8d53ae28be399899d0a5a7617cff1dce5d656b06",
      "prizes": {
        "5": [
          489
        ]
      }
    },
    {
      "user": "0x2d93f264370bf61f8759470a906528ad6937a47a",
      "prizes": {
        "5": [
          202,
          642,
          848
        ]
      }
    },
    {
      "user": "0x6b44862103b8a45f5ec701b69ec28a5d6d304950",
      "prizes": {
        "5": [
          122
        ]
      }
    },
    {
      "user": "0x157c41a2a1b4e5810be2b009c093f3d78945c1db",
      "prizes": {
        "5": [
          270,
          605
        ]
      }
    },
    {
      "user": "0x11a540cd590eb00d38954aab0f6f28deec5a5635",
      "prizes": {
        "5": [
          901
        ]
      }
    },
    {
      "user": "0x803585733d4554e712dcacc2acea3a23b96de1e0",
      "prizes": {
        "5": [
          37
        ]
      }
    },
    {
      "user": "0x093e4ab2665d17e66eff0e79460cb53659195275",
      "prizes": {
        "5": [
          402
        ]
      }
    },
    {
      "user": "0x1b52c00fd9dc204ad4e98c52c2b691f15acd1b60",
      "prizes": {
        "5": [
          852
        ]
      }
    },
    {
      "user": "0x0efb1e87d0f5b86e28f6da90da76d561f9c9a1f6",
      "prizes": {
        "5": [
          568
        ]
      }
    },
    {
      "user": "0x6d436d88dc7b6d66b4441781e8d9993bc13c27e3",
      "prizes": {
        "5": [
          4,
          64,
          369,
          774
        ]
      }
    },
    {
      "user": "0x205389a3a0ba0928f9c696fb29cbb3edc66183be",
      "prizes": {
        "5": [
          973
        ]
      }
    },
    {
      "user": "0xbf4c544b70100d72c5c40e4521b600fe62a22b87",
      "prizes": {
        "5": [
          111
        ]
      }
    },
    {
      "user": "0x929a478b65ead807b8e3d1999db494dcff41b043",
      "prizes": {
        "5": [
          138,
          395,
          577,
          755,
          834,
          986
        ]
      }
    },
    {
      "user": "0x9ffaa816a11a5e36ba911f157cc8d0734cc4ca2d",
      "prizes": {
        "5": [
          549,
          756
        ]
      }
    },
    {
      "user": "0x7998bcb66e51a49be8e31a31b957bcd02c8ded6e",
      "prizes": {
        "5": [
          743
        ]
      }
    },
    {
      "user": "0xdd45ca901067d65860b54d4310e37371cd92fb09",
      "prizes": {
        "5": [
          923
        ]
      }
    },
    {
      "user": "0xd917eb4dcfccf91e6496702bc6309d5a59eef713",
      "prizes": {
        "5": [
          284,
          668,
          963
        ]
      }
    },
    {
      "user": "0x7bb672e35c75fdfe483ee88abd6079ad1b9fde79",
      "prizes": {
        "5": [
          949
        ]
      }
    },
    {
      "user": "0x175c4f84f41bd3dc37a42d8260f57bc5475e9753",
      "prizes": {
        "5": [
          404,
          862
        ]
      }
    },
    {
      "user": "0x837cbfc411095fb3e1e9cf4fdcf1a6d5d8c525b5",
      "prizes": {
        "5": [
          131
        ]
      }
    },
    {
      "user": "0xa192ad6f0466ba61b5c26c3be6d1997fad1ce2fe",
      "prizes": {
        "5": [
          212
        ]
      }
    },
    {
      "user": "0xffd55d121713682b27fd4ad42270461830c45a3e",
      "prizes": {
        "5": [
          8
        ]
      }
    },
    {
      "user": "0x50d9753d966764b068c56493d0f8b0296ab0b24e",
      "prizes": {
        "5": [
          581,
          750,
          802
        ]
      }
    },
    {
      "user": "0xd836da33a6629548271eb9ef4f62d083376eb4a6",
      "prizes": {
        "5": [
          525
        ]
      }
    },
    {
      "user": "0xc9a2ba82b78fd8d85aa265f6a6cd3a1054350ca4",
      "prizes": {
        "5": [
          733
        ]
      }
    },
    {
      "user": "0xa6e103824673013dce211f683551ce18cdc1e3b3",
      "prizes": {
        "5": [
          273
        ]
      }
    },
    {
      "user": "0x79f94ae8a65b331afef665ad628fb2853c2ef307",
      "prizes": {
        "5": [
          579
        ]
      }
    },
    {
      "user": "0x742cf00544b816f36a2d286631050f8fc8755dc2",
      "prizes": {
        "5": [
          753
        ]
      }
    },
    {
      "user": "0xfa4a45d755ea1c2b72dd581b3e05dde3bfc13fad",
      "prizes": {
        "5": [
          153
        ]
      }
    },
    {
      "user": "0xaa83acb29b45e58c8a0b77b10a457ee63eaffbda",
      "prizes": {
        "5": [
          187
        ]
      }
    },
    {
      "user": "0x2225b32aebf89888821ec7dd59dcbc653b49f6aa",
      "prizes": {
        "5": [
          581
        ]
      }
    },
    {
      "user": "0x8aeb24ba4a9f25ead8609ee3bc6f52ac8d49ad3b",
      "prizes": {
        "5": [
          715
        ]
      }
    },
    {
      "user": "0x1374376a0aac0d54b5f19ce0b7ed32be2d03c9cd",
      "prizes": {
        "5": [
          807
        ]
      }
    },
    {
      "user": "0x54c1632c049ff4a1e36b81e5d1d8f079cfdb8505",
      "prizes": {
        "5": [
          35
        ]
      }
    },
    {
      "user": "0x89a7f580f121725644b3219949eaf256cb794afa",
      "prizes": {
        "5": [
          315
        ]
      }
    },
    {
      "user": "0x544e93c8cc446d4fd761d47c0ffcb1495fd86fc4",
      "prizes": {
        "5": [
          298,
          800
        ]
      }
    },
    {
      "user": "0xd167ce49b3cf9392a3f8893c9a29ebc3195b6a3e",
      "prizes": {
        "5": [
          816
        ]
      }
    },
    {
      "user": "0x050ad495aba11b3b47657d3a8f064f0e9e31233f",
      "prizes": {
        "5": [
          858
        ]
      }
    },
    {
      "user": "0x09080e4ffa4c08815cf53d157551cd409fe0a1f0",
      "prizes": {
        "5": [
          139,
          1015
        ]
      }
    },
    {
      "user": "0xa666ee932da1503601b364c18dd7d84391075e7e",
      "prizes": {
        "5": [
          1013
        ]
      }
    },
    {
      "user": "0xd7cec4270166398dd0cc927e66a46546dc59e29a",
      "prizes": {
        "5": [
          546
        ]
      }
    },
    {
      "user": "0xd9e7c440039a9c99b175de70cecaf1b7be8f121b",
      "prizes": {
        "5": [
          129,
          147,
          221,
          610,
          611,
          612
        ]
      }
    },
    {
      "user": "0x82f402847051bddaab0f5d4b481417281837c424",
      "prizes": {
        "5": [
          147,
          1011
        ]
      }
    },
    {
      "user": "0xe5c4462b2b59d75f572464388372f1b97f70aff7",
      "prizes": {
        "5": [
          1018
        ]
      }
    },
    {
      "user": "0x4c0713d9eb4efd10ccf4d459630f4652723c9f30",
      "prizes": {
        "5": [
          128,
          223,
          351,
          495,
          609,
          874,
          959
        ]
      }
    },
    {
      "user": "0xd4785e5e90929af38edc514a8a860691cca606ad",
      "prizes": {
        "5": [
          83,
          133,
          190,
          305,
          466,
          629
        ]
      }
    },
    {
      "user": "0xb47427b1698f9c31858180b769a093b3027f294f",
      "prizes": {
        "5": [
          246,
          697
        ]
      }
    },
    {
      "user": "0x44af89b345b09aeeffc175bf43c2502d77e1a76a",
      "prizes": {
        "5": [
          716
        ]
      }
    },
    {
      "user": "0xebef7c82957264737745c11b6892b512e0cbea3e",
      "prizes": {
        "5": [
          392,
          800
        ]
      }
    },
    {
      "user": "0x8c659e4b2e5e3966314c7f3574f8e0b636718237",
      "prizes": {
        "5": [
          716
        ]
      }
    },
    {
      "user": "0x5dea60eef2bfcef3a808a219b562145d1b80bd7d",
      "prizes": {
        "5": [
          430
        ]
      }
    },
    {
      "user": "0x5c9db9f19c35130c696e19ab60fbb8955ddaf29d",
      "prizes": {
        "5": [
          391
        ]
      }
    },
    {
      "user": "0xf827415923b5d7c0acfba34b0c9249e21ea88009",
      "prizes": {
        "5": [
          1008
        ]
      }
    },
    {
      "user": "0xb89729bc7eebbfad2f3dd073ee8f200d1116ae8b",
      "prizes": {
        "5": [
          644,
          695,
          763
        ]
      }
    },
    {
      "user": "0xe47d91f4c4991d39a2f3a08baa7f1c296f0d72fd",
      "prizes": {
        "5": [
          373
        ]
      }
    },
    {
      "user": "0x007774e30694f165ce8681165bb24584897fa2c2",
      "prizes": {
        "5": [
          493
        ]
      }
    },
    {
      "user": "0x505aa104869783f1ed411339862a54041eb57162",
      "prizes": {
        "5": [
          20,
          193,
          471,
          528,
          754,
          909
        ]
      }
    },
    {
      "user": "0xfffb0fe5e806d7a608a23be69b390eb24936db01",
      "prizes": {
        "5": [
          905
        ]
      }
    },
    {
      "user": "0x7ebd5f813e9bac793fba073e98bc06ae89763eec",
      "prizes": {
        "5": [
          384
        ]
      }
    },
    {
      "user": "0x7797fa88f7f2988a2a278a4f4cc1f48a9aa1b20e",
      "prizes": {
        "5": [
          101,
          884
        ]
      }
    },
    {
      "user": "0x0843605971ffde77b6065bc6650967380da7dc29",
      "prizes": {
        "5": [
          672
        ]
      }
    },
    {
      "user": "0xf112f84c28795172cf998ea5d2a5993f78ccbddf",
      "prizes": {
        "5": [
          77,
          165,
          971
        ]
      }
    },
    {
      "user": "0x430e225f43549f9ad06e5e68137bec8bb4071f97",
      "prizes": {
        "5": [
          32,
          680
        ]
      }
    },
    {
      "user": "0xf61397e4b0ff46e78b34d5f72b49b4d46e8c96dd",
      "prizes": {
        "5": [
          151,
          157,
          367,
          887
        ]
      }
    },
    {
      "user": "0x85fbec0d141722b596121ec3e53765f35731c502",
      "prizes": {
        "5": [
          520
        ]
      }
    },
    {
      "user": "0x3873decd4f853bad034b6c035a9b494d7161f9ba",
      "prizes": {
        "5": [
          523
        ]
      }
    },
    {
      "user": "0xb9147c6a00e82a908bdf4ea4c326ca280ba80f47",
      "prizes": {
        "5": [
          82
        ]
      }
    },
    {
      "user": "0xe0aaec9c2a93c262ca56bc22ea0b404f6dcfa776",
      "prizes": {
        "5": [
          329
        ]
      }
    },
    {
      "user": "0x17335aca967138083b04dc70cef828c83f5b6160",
      "prizes": {
        "5": [
          196
        ]
      }
    },
    {
      "user": "0x7483baa036b09fa0df6cce5f9194e4651a36830a",
      "prizes": {
        "5": [
          238
        ]
      }
    },
    {
      "user": "0x368a3217ded4c5986db39bcc22932b209eb17026",
      "prizes": {
        "5": [
          519
        ]
      }
    },
    {
      "user": "0x5584541f0fd8561455c211e10b5c9750fdd62fbb",
      "prizes": {
        "5": [
          693
        ]
      }
    },
    {
      "user": "0xebcadf08f64012787f2f4dde99b13fe1183b72e2",
      "prizes": {
        "5": [
          264,
          779
        ]
      }
    },
    {
      "user": "0xe574c8c474beaf5413f404894eee7432856d28fd",
      "prizes": {
        "5": [
          1015
        ]
      }
    },
    {
      "user": "0x5a31722a0687b09c8332b2d61c2f4566de14ad00",
      "prizes": {
        "5": [
          366
        ]
      }
    },
    {
      "user": "0xb86c3b0a32e8dacb483ca7c787a8b258470e3f93",
      "prizes": {
        "5": [
          774
        ]
      }
    },
    {
      "user": "0x19bc334ab56c18128c188a6543acb49c84b43c2e",
      "prizes": {
        "5": [
          787
        ]
      }
    },
    {
      "user": "0x41f0f58c59b61fdea51c1901a316838e1311bfee",
      "prizes": {
        "5": [
          468
        ]
      }
    },
    {
      "user": "0x7af5a23d180e6dff260b3b241a253a90f0ff8048",
      "prizes": {
        "5": [
          141,
          730
        ]
      }
    },
    {
      "user": "0x2a131a477467e1998fe7290a1f5377f51cb8238d",
      "prizes": {
        "5": [
          957
        ]
      }
    }
  ],
  "0x051264d4c1a576cb423c350c973fe0b748e4170f": [],
  "0x11271bf9855b679bc484a0c80a69d8cc72fcef89": [
    {
      "user": "0x51bc9862ad17023fa88435f51fcaa6e677b2ca97",
      "prizes": {
        "3": [
          59
        ],
        "4": [
          10,
          13,
          40
        ],
        "5": [
          67,
          150,
          370,
          432,
          475,
          644,
          692,
          703,
          760,
          956
        ]
      }
    },
    {
      "user": "0x8374b71ca50342434c2d6add696c245693c4237b",
      "prizes": {
        "4": [
          152
        ]
      }
    },
    {
      "user": "0x5584541f0fd8561455c211e10b5c9750fdd62fbb",
      "prizes": {
        "4": [
          84
        ],
        "5": [
          843,
          950
        ]
      }
    },
    {
      "user": "0x6d436d88dc7b6d66b4441781e8d9993bc13c27e3",
      "prizes": {
        "4": [
          102
        ],
        "5": [
          128,
          190,
          364,
          373,
          557,
          709,
          802,
          892,
          981,
          989
        ]
      }
    },
    {
      "user": "0xa555cf7e7e04919e653577ff76fe44e119a018cc",
      "prizes": {
        "4": [
          205
        ],
        "5": [
          482
        ]
      }
    },
    {
      "user": "0x174976a7bae6bf9abb80a7bd6896a78fbd17386d",
      "prizes": {
        "5": [
          761
        ]
      }
    },
    {
      "user": "0x8a1ec127978bcc7499b2a188df2bd1810f522ac7",
      "prizes": {
        "5": [
          442,
          663
        ]
      }
    },
    {
      "user": "0xd9ec650cfbc557f03c565f5189ec31fedbee43a5",
      "prizes": {
        "5": [
          159,
          270,
          580,
          801
        ]
      }
    },
    {
      "user": "0xa8033118b5393bceda847e62eb69a03188cb4a89",
      "prizes": {
        "5": [
          260
        ]
      }
    },
    {
      "user": "0xe782657a1043062087232b3c20c4d25e2a982cb3",
      "prizes": {
        "5": [
          349
        ]
      }
    }
  ],
  "0x171d898849cd21a1ca6e111933dad1f5b8664c88": [],
  "0x182d3050f7261494757638ff3345c7163e5990f3": [],
  "0x1f16d3ccf568e96019cedc8a2c79d2ca6257894e": [
    {
      "user": "0xa6a49d09321f701ab4295e5eb115e65ecf9b83b5",
      "prizes": {
        "4": [
          26
        ],
        "5": [
          961
        ]
      }
    },
    {
      "user": "0x97116661c85c4e1ee35aa10f7fc5fe5e67b83a5b",
      "prizes": {
        "5": [
          96,
          901
        ]
      }
    },
    {
      "user": "0x7b22fda532f9f9fb688e502d4caf7b2b9bd36a26",
      "prizes": {
        "5": [
          101,
          214,
          966
        ]
      }
    },
    {
      "user": "0x0d8163aee1bec6338b979e34b6cb31013fe82516",
      "prizes": {
        "5": [
          499
        ]
      }
    }
  ],
  "0x2998c1685e308661123f64b333767266035f5020": [
    {
      "user": "0xad2d5bdc3c2dd575c0fa8b70b4f9dfc74b5c1590",
      "prizes": {
        "4": [
          21,
          87,
          93,
          174
        ],
        "5": [
          190,
          241,
          466,
          565,
          611,
          789,
          1004
        ]
      }
    },
    {
      "user": "0xf77e2c9b9ea81843d97a034e50aaa61b54edcc92",
      "prizes": {
        "4": [
          205
        ]
      }
    },
    {
      "user": "0x4550fc7cd7351f2a35d0af445bb4a9c3cf826683",
      "prizes": {
        "4": [
          150
        ],
        "5": [
          592
        ]
      }
    },
    {
      "user": "0x2f358e304115bb32ec76899965fc5b91a23cabe1",
      "prizes": {
        "4": [
          245
        ],
        "5": [
          964
        ]
      }
    },
    {
      "user": "0x501d66e0b4254de6187443b9cdb744e2752f489e",
      "prizes": {
        "4": [
          127
        ],
        "5": [
          422
        ]
      }
    },
    {
      "user": "0x505aa104869783f1ed411339862a54041eb57162",
      "prizes": {
        "4": [
          123,
          153
        ],
        "5": [
          191
        ]
      }
    },
    {
      "user": "0x174976a7bae6bf9abb80a7bd6896a78fbd17386d",
      "prizes": {
        "4": [
          8,
          65,
          74,
          96,
          170,
          252
        ],
        "5": [
          11,
          45,
          48,
          64,
          68,
          114,
          137,
          174,
          243,
          255,
          260,
          273,
          311,
          349,
          369,
          470,
          475,
          492,
          521,
          600,
          619,
          762,
          815,
          823,
          832,
          874,
          902,
          912,
          919,
          921,
          976
        ]
      }
    },
    {
      "user": "0x3d713067761725e6a237e5a0572aa47348eafe3d",
      "prizes": {
        "4": [
          66,
          120
        ],
        "5": [
          6,
          30,
          71,
          76,
          379,
          510,
          546,
          654,
          722,
          729,
          778,
          868
        ]
      }
    },
    {
      "user": "0xe2d31a02163d2a49aebd19aefcd43b9119700fcf",
      "prizes": {
        "4": [
          58
        ]
      }
    },
    {
      "user": "0x2e1db2e75e05a7137b9386d0cecebea8a92187b5",
      "prizes": {
        "4": [
          96,
          135,
          224
        ],
        "5": [
          693,
          849,
          882
        ]
      }
    },
    {
      "user": "0x22145b2537edb0a45455b3bee3fe2aab2f27c598",
      "prizes": {
        "4": [
          6
        ]
      }
    },
    {
      "user": "0x66cfd050e328737f3e9ad9262c068c5b2ba4390b",
      "prizes": {
        "4": [
          110
        ],
        "5": [
          34,
          35,
          53,
          359,
          465,
          514,
          536,
          945,
          992
        ]
      }
    },
    {
      "user": "0xd70804463bb2760c3384fc87bbe779e3d91bab3a",
      "prizes": {
        "4": [
          122,
          243
        ],
        "5": [
          245,
          635,
          726,
          873
        ]
      }
    },
    {
      "user": "0x798a52edcb6f22d5da1896ef924f1d4c35bca686",
      "prizes": {
        "4": [
          40
        ],
        "5": [
          121
        ]
      }
    },
    {
      "user": "0xd455992691f18b447823dd12c28bc31626706244",
      "prizes": {
        "3": [
          50
        ],
        "4": [
          169
        ],
        "5": [
          148,
          291,
          672,
          964
        ]
      }
    },
    {
      "user": "0xa6e029548152f098416c0ad60c18930b4f8619c6",
      "prizes": {
        "4": [
          76
        ],
        "5": [
          201
        ]
      }
    },
    {
      "user": "0x5dea60eef2bfcef3a808a219b562145d1b80bd7d",
      "prizes": {
        "4": [
          245
        ]
      }
    },
    {
      "user": "0x9f36a6bb398118bdcd5b1bc3343d8feb6d7d02b9",
      "prizes": {
        "4": [
          49,
          57
        ],
        "5": [
          111,
          668,
          808,
          981
        ]
      }
    },
    {
      "user": "0x897d24557116f39440fab68feb0ed97bbbeaeeed",
      "prizes": {
        "4": [
          122,
          153
        ],
        "5": [
          221,
          642,
          656,
          674
        ]
      }
    },
    {
      "user": "0xfb96d3340ab2452955f667615c9f51115ae55dcc",
      "prizes": {
        "4": [
          115
        ],
        "5": [
          366,
          737
        ]
      }
    },
    {
      "user": "0x79e09a74f03b0683a950887e2387cffbf244d497",
      "prizes": {
        "4": [
          41
        ]
      }
    },
    {
      "user": "0x44989d681071171956445bc2a8e00d614e3358c0",
      "prizes": {
        "4": [
          163
        ],
        "5": [
          13,
          102,
          697,
          754
        ]
      }
    },
    {
      "user": "0x57a482ea32c7f75a9c0734206f5bd4f9bcb38e12",
      "prizes": {
        "4": [
          134
        ],
        "5": [
          100
        ]
      }
    },
    {
      "user": "0x7692a4436f8252f34258c2bfa846ec5e840d5e55",
      "prizes": {
        "4": [
          190
        ],
        "5": [
          38,
          201,
          787,
          1008
        ]
      }
    },
    {
      "user": "0x819b2886cb636db6098e6f0e52aa6a30b5cff1bb",
      "prizes": {
        "5": [
          81,
          860
        ]
      }
    },
    {
      "user": "0xfeeb4ed5029fa0febe1dbc87fe20ba1118dca49b",
      "prizes": {
        "5": [
          253,
          550,
          652,
          846,
          965
        ]
      }
    },
    {
      "user": "0xf05e4f44de569cf8c6acf5fce98271008a532969",
      "prizes": {
        "5": [
          924
        ]
      }
    },
    {
      "user": "0xb1d86fd92b9a6900610a8c9789e5eb2431444f6c",
      "prizes": {
        "5": [
          1,
          879
        ]
      }
    },
    {
      "user": "0xe0e7b7c5ae92fe94d2ae677d81214d6ad7a11c27",
      "prizes": {
        "5": [
          167,
          453,
          615,
          647,
          671
        ]
      }
    },
    {
      "user": "0x42b1d175e813c143314864da54453920e7d60e2b",
      "prizes": {
        "5": [
          993
        ]
      }
    },
    {
      "user": "0x6d436d88dc7b6d66b4441781e8d9993bc13c27e3",
      "prizes": {
        "5": [
          393
        ]
      }
    },
    {
      "user": "0xa8078cabce440b0feadd7264adf179d301fcef18",
      "prizes": {
        "5": [
          322
        ]
      }
    },
    {
      "user": "0xa05f2774ba121531da7c1bb7fe437aaf881c71b6",
      "prizes": {
        "5": [
          124
        ]
      }
    },
    {
      "user": "0xf7467feb2c0b271dfffcdb9c928f0bf546575a87",
      "prizes": {
        "5": [
          836,
          1020
        ]
      }
    },
    {
      "user": "0x139f7e58c4ba8c98d45ef9fcbe2ddce810002baa",
      "prizes": {
        "5": [
          212,
          668
        ]
      }
    },
    {
      "user": "0xb64cb2f1c722a6d9dc6b768f05acaad64d80eaf9",
      "prizes": {
        "5": [
          598
        ]
      }
    },
    {
      "user": "0x197a78fe1bd3bbb64c1325c027bde8f67bac1770",
      "prizes": {
        "5": [
          715
        ]
      }
    },
    {
      "user": "0xda9cb21f6b662eb972ecc8fd358a1fdab0811977",
      "prizes": {
        "5": [
          620
        ]
      }
    },
    {
      "user": "0x3d6facad1f5c6463e592c94a2a316a7697ad9de0",
      "prizes": {
        "5": [
          406
        ]
      }
    },
    {
      "user": "0x675233348fc519cbcf70fe75c26856501327fee1",
      "prizes": {
        "5": [
          386,
          396
        ]
      }
    },
    {
      "user": "0x1a59e9c02ec869065e301cfcc0ce7835e94ec07f",
      "prizes": {
        "5": [
          695
        ]
      }
    },
    {
      "user": "0x32ad379d17a523c79cba370a2bd645637ed4f4af",
      "prizes": {
        "5": [
          590
        ]
      }
    },
    {
      "user": "0x8ae715283ed6617963c0001c3074f574dbb70d9a",
      "prizes": {
        "5": [
          699
        ]
      }
    },
    {
      "user": "0x44704724fd058ca0c6f3b3ad2b06de65110f4c26",
      "prizes": {
        "5": [
          174,
          236,
          464,
          671
        ]
      }
    },
    {
      "user": "0x6156ec8cafc48f50f2747a4dad9c0937c0d1c459",
      "prizes": {
        "5": [
          482,
          655,
          837
        ]
      }
    },
    {
      "user": "0xa38445311ccd04a54183cdd347e793f4d548df3f",
      "prizes": {
        "5": [
          164,
          1022
        ]
      }
    }
  ],
  "0x2a015a66dd75b60423414d508078e8666b7771d7": [],
  "0x35b92060f56cc9be483c91a581647387ff3e5c84": [],
  "0x363b7a1567af0dbf06642c4028779c3f3365b516": [],
  "0x37e49c9dbf195f5d436c7a7610fe703cdcd8147b": [],
  "0x395ae52bb17aef68c2888d941736a71dc6d4e125": [],
  "0x3d87b066dcf93661c66cd5158a449483259a3bc1": [],
  "0x3e8dbe51da479f7e8ac46307af99ad5b4b5b41dc": [
    {
      "user": "0xbb7724d5fc4af70489b66d13b4f19361b1e31457",
      "prizes": {
        "4": [
          233
        ],
        "5": [
          239,
          302,
          369,
          631,
          638,
          815,
          849,
          962
        ]
      }
    },
    {
      "user": "0x5e397021f3c38f594e5c8a2ec8ec79faf6145c8c",
      "prizes": {
        "4": [
          214
        ]
      }
    },
    {
      "user": "0xf45ce3921f25677802b0f32b1664ba55535264be",
      "prizes": {
        "4": [
          185
        ],
        "5": [
          276,
          393,
          973
        ]
      }
    },
    {
      "user": "0xc4eaf72bc568d82bd82e7a1c1c0d0fc536984dc7",
      "prizes": {
        "4": [
          158
        ],
        "5": [
          327
        ]
      }
    },
    {
      "user": "0xdcb7c03c06fde7976de5d179b44e8367942fb8d5",
      "prizes": {
        "4": [
          59
        ]
      }
    },
    {
      "user": "0x174976a7bae6bf9abb80a7bd6896a78fbd17386d",
      "prizes": {
        "4": [
          252
        ],
        "5": [
          59,
          102,
          231
        ]
      }
    },
    {
      "user": "0x9f36a6bb398118bdcd5b1bc3343d8feb6d7d02b9",
      "prizes": {
        "4": [
          21
        ],
        "5": [
          323,
          473,
          683,
          919
        ]
      }
    },
    {
      "user": "0x6b44862103b8a45f5ec701b69ec28a5d6d304950",
      "prizes": {
        "5": [
          330
        ]
      }
    },
    {
      "user": "0xd455992691f18b447823dd12c28bc31626706244",
      "prizes": {
        "5": [
          915
        ]
      }
    },
    {
      "user": "0x6eba83ac495f7db36f398aeffbcd0fb6f21aab7e",
      "prizes": {
        "5": [
          418,
          726
        ]
      }
    },
    {
      "user": "0xd53d36f66ca025bbe2a089f5dc59e3235c4327d3",
      "prizes": {
        "5": [
          116,
          413,
          689,
          715
        ]
      }
    },
    {
      "user": "0x0d3d681762f9eda9541fab6acfb17c50025b630b",
      "prizes": {
        "5": [
          383
        ]
      }
    },
    {
      "user": "0x9b2247e137387c2a2c49e9607e4b70473891e9fc",
      "prizes": {
        "5": [
          390,
          909,
          990
        ]
      }
    },
    {
      "user": "0xa6e029548152f098416c0ad60c18930b4f8619c6",
      "prizes": {
        "5": [
          112,
          760
        ]
      }
    },
    {
      "user": "0xc632b0c926291da28f8496d4f33cbe1f454e6f64",
      "prizes": {
        "5": [
          96,
          582,
          989
        ]
      }
    }
  ],
  "0x4200000000000000000000000000000000000042": [],
  "0x426783a67d34149c5fd13ab233de4caf5f7ca7b6": [],
  "0x449b6a60501015c1a8fda6cd97147280f5eb33d7": [
    {
      "user": "0xc694108e704b3ac3c5b099a4b06208bd0695ad00",
      "prizes": {
        "5": [
          345
        ]
      }
    },
    {
      "user": "0x5df178dce46e35ddd122f6cda1468a91ea819e67",
      "prizes": {
        "5": [
          545
        ]
      }
    }
  ],
  "0x46ec15aed8645154a3a276c007ac5b99d8d7067c": [],
  "0x4b9a4edbdb67ee8d880964732c1f56e4c13f2c04": [],
  "0x5c458df58c2a4253f07ae416e8828ccbdbb2974a": [],
  "0x5eb32e6dec24d58c14d21fd1b329d9f65de58364": [],
  "0x5fbfe2ef7f7396269356ce3bb673fc3fdd2c3468": [],
  "0x5fd190357eccf07f558e48f1f85ed184ee211e53": [],
  "0x61c15203aa2745d5fda730268cb4efa46b962db0": [],
  "0x626f8282f712732be0c12d4a89a86be6e9ce8ac8": [],
  "0x7889366a039d92dd6aa12ce8f6fb027c3b7e397c": [],
  "0x7affb8cb92ddf9f9d0ba6fdcd7cd7905cb6d2ec1": [],
  "0x896232c67eba02033334008f21767fe586792c52": [],
  "0x8b47c737179cb1354e8950acec6bd43f26af0290": [],
  "0x8c2f27b7819eb1bb7e3b5c407c5e1839186d5aba": [],
  "0x934c51eedbd0d558ab1c171498271930b4716295": [],
  "0x9b4c0de59628c64b02d7ce86f21db9a579539d5a": [],
  "0x9b53ef6f13077727d22cb4acad1119c79a97be17": [
    {
      "user": "0x74a5c89b08e7e719384ea230591187d041f68c88",
      "prizes": {
        "5": [
          586
        ]
      }
    },
    {
      "user": "0x057880e32656dee0cacd1188cc231e13a80dac65",
      "prizes": {
        "5": [
          271,
          736
        ]
      }
    },
    {
      "user": "0xe48dd2a322a7ebfdaa9680fd2e8cec27cbb7a765",
      "prizes": {
        "5": [
          51,
          154,
          466,
          673
        ]
      }
    },
    {
      "user": "0xb44b6442b731d9954819470f6f528aa3e65dff15",
      "prizes": {
        "5": [
          598
        ]
      }
    },
    {
      "user": "0x266183d3636b70118aa5aeb78c6f6d5102377c17",
      "prizes": {
        "5": [
          108,
          273
        ]
      }
    },
    {
      "user": "0x3d6facad1f5c6463e592c94a2a316a7697ad9de0",
      "prizes": {
        "5": [
          0,
          111
        ]
      }
    },
    {
      "user": "0x9b53ef6f13077727d22cb4acad1119c79a97be17",
      "prizes": {
        "4": [
          38,
          99,
          100,
          146,
          171,
          234,
          243
        ],
        "5": [
          48,
          166,
          219,
          221,
          353,
          389,
          404,
          514,
          541,
          741,
          743,
          769,
          787,
          794,
          843,
          883
        ]
      }
    },
    {
      "user": "0x29bbf26fc9628d076094c20f0cea51142bbc4aa5",
      "prizes": {
        "4": [
          46,
          145,
          184,
          232
        ],
        "5": [
          28,
          64,
          87,
          104,
          159,
          226,
          247,
          384,
          486,
          494,
          516,
          535,
          676,
          769,
          771,
          932,
          960,
          1018
        ]
      }
    },
    {
      "user": "0x3734a56df481c5b168cd14a20545f62db03568d2",
      "prizes": {
        "5": [
          2
        ]
      }
    },
    {
      "user": "0xbfaf0a4d237965b7bd0704f7ea884e5097bc92a4",
      "prizes": {
        "4": [
          108
        ]
      }
    }
  ],
  "0xa46de5b77dbe59a7b9213f3dd1634da25e7e3bfb": [],
  "0xa52e38a9147f5ea9e0c5547376c21c9e3f3e5e1f": [
    {
      "user": "0x5f3188b55e0d3320f2ba558fa9f365009998c401",
      "prizes": {
        "5": [
          149
        ]
      }
    },
    {
      "user": "0xaf58eb031b84cf28a402c1c8fcbe7bac635a8484",
      "prizes": {
        "5": [
          375
        ]
      }
    },
    {
      "user": "0x174976a7bae6bf9abb80a7bd6896a78fbd17386d",
      "prizes": {
        "5": [
          232,
          354,
          527,
          569,
          858
        ]
      }
    },
    {
      "user": "0xa9319788fbe9c977193558632f48a7e1348afce7",
      "prizes": {
        "5": [
          110
        ]
      }
    },
    {
      "user": "0x29bbf26fc9628d076094c20f0cea51142bbc4aa5",
      "prizes": {
        "5": [
          187
        ]
      }
    },
    {
      "user": "0x7032bebd3b9ea25a6d34bf476d1a569b7043a232",
      "prizes": {
        "5": [
          235
        ]
      }
    },
    {
      "user": "0x6a023e522b1813c4de392007f941625fd62464b4",
      "prizes": {
        "5": [
          996
        ]
      }
    },
    {
      "user": "0xa8078cabce440b0feadd7264adf179d301fcef18",
      "prizes": {
        "3": [
          33
        ],
        "5": [
          289
        ]
      }
    },
    {
      "user": "0xa7329fd51b2dc832f92a1ec5e05cc35d4d1a095e",
      "prizes": {
        "4": [
          11,
          83,
          130,
          142
        ],
        "5": [
          18,
          119,
          212,
          241,
          377,
          611,
          840,
          899,
          930
        ]
      }
    },
    {
      "user": "0x505aa104869783f1ed411339862a54041eb57162",
      "prizes": {
        "5": [
          340
        ]
      }
    },
    {
      "user": "0x4cd7a2a984ced0c9f7316b2b4427601e6db87b30",
      "prizes": {
        "5": [
          47
        ]
      }
    },
    {
      "user": "0x3dddb2407ecb8df5469352d84238d087287cbb5b",
      "prizes": {
        "4": [
          96
        ],
        "5": [
          627,
          681,
          727
        ]
      }
    },
    {
      "user": "0x57a482ea32c7f75a9c0734206f5bd4f9bcb38e12",
      "prizes": {
        "5": [
          47
        ]
      }
    },
    {
      "user": "0xccd72bea12f3927063be3d8798a4b74082713cb5",
      "prizes": {
        "4": [
          53
        ],
        "5": [
          35,
          150,
          272,
          305,
          315,
          339,
          411,
          446,
          563,
          693,
          995
        ]
      }
    },
    {
      "user": "0xd917eb4dcfccf91e6496702bc6309d5a59eef713",
      "prizes": {
        "5": [
          533
        ]
      }
    },
    {
      "user": "0xfbcfd0a67bbc544ff547d04d28b8ff1ea4b9d116",
      "prizes": {
        "5": [
          110,
          156,
          160
        ]
      }
    },
    {
      "user": "0x6d436d88dc7b6d66b4441781e8d9993bc13c27e3",
      "prizes": {
        "4": [
          243
        ],
        "5": [
          214
        ]
      }
    },
    {
      "user": "0x733a53a044346aac1c4bdd64e7f9eddc36c443e1",
      "prizes": {
        "4": [
          59
        ],
        "5": [
          825
        ]
      }
    },
    {
      "user": "0x8e49d2574042611cf30551e90d37d7b2c08b7028",
      "prizes": {
        "5": [
          265,
          764
        ]
      }
    },
    {
      "user": "0xb623352e078e57349fe5a8de96109e2395cb20fe",
      "prizes": {
        "5": [
          583
        ]
      }
    },
    {
      "user": "0x0d3d681762f9eda9541fab6acfb17c50025b630b",
      "prizes": {
        "5": [
          932
        ]
      }
    },
    {
      "user": "0x649c92a98b8c163de6bba53effd55ad2d89553b7",
      "prizes": {
        "5": [
          736
        ]
      }
    },
    {
      "user": "0x1a59e9c02ec869065e301cfcc0ce7835e94ec07f",
      "prizes": {
        "5": [
          7
        ]
      }
    },
    {
      "user": "0x04e8672877425110d4ddc31955233e7af7775072",
      "prizes": {
        "4": [
          219,
          252
        ],
        "5": [
          284
        ]
      }
    },
    {
      "user": "0xf756e4368a03627eac9b0c474c8420794f429ba1",
      "prizes": {
        "5": [
          133,
          308,
          677,
          724
        ]
      }
    },
    {
      "user": "0x31e0cd40fd6246e389373cf997704c0f9ba84fd8",
      "prizes": {
        "4": [
          209
        ]
      }
    },
    {
      "user": "0xe24bc6c67fef2ffe40283c1359dce44bd19c72c4",
      "prizes": {
        "4": [
          29
        ]
      }
    },
    {
      "user": "0x07fe778a439aebc7cdac18d0f608166873d17039",
      "prizes": {
        "4": [
          107
        ]
      }
    },
    {
      "user": "0xe9fbd0a3703a487dbe8facb48288deb267596eaa",
      "prizes": {
        "4": [
          16,
          127
        ]
      }
    },
    {
      "user": "0xcc22f7f6a8296ed44f0f0e758374675120909177",
      "prizes": {
        "4": [
          82
        ]
      }
    },
    {
      "user": "0xe22776140b65f3c56562c26a7f76b0fe6476d6b9",
      "prizes": {
        "4": [
          255
        ]
      }
    }
  ],
  "0xa58163334eba40fa6e81a77c2b36f252a945928a": [],
  "0xa74997653ee4c8a60989161c621b042414413111": [],
  "0xb0be8eab1cba26963f382fbc36aaff9e7b89244c": [],
  "0xb4063d1f0b0b7caee88708895ec4e365bf44b984": [],
  "0xb4911efd3d53352f658536afd37e7897cb7dd7f6": [],
  "0xb61bf70e978f7260768c26d8737f6dbd5778360c": [],
  "0xbfadf0d82f891042352f83d0f1bdeddaf1181cf3": [],
  "0xcc3fefb704be360245f8dd0386ac206941e66467": [],
  "0xcf6abb37336e3a756b564e2c29222bf187a0de2a": [],
  "0xd9825b290bab900d84f341ddbf9f96b71bac39b2": [],
  "0xdaaf4b68b1299fb9b05ae578cb3d06c8528138d4": [],
  "0xdeef914a2ee2f2014ce401dcb4e13f6540d20ba7": [],
  "0xe13ee913c132af8c4887a6c037c0da10b6d43d18": [],
  "0xe2778b7c04a44dc8480fee88edc3cef8ee11fce0": [],
  "0xe5f8c4e783839e14080daf3e28d64e3140596989": [],
  "0xed953dcc2e93224a94944bf8fd6420324515e7c4": [],
  "0xefd811808b2366fa07d9dc5f8c64046a421a5e97": [],
  "0xf1d934d5a3c6e530ac1450c92af5ba01eb90d4de": [],
  "0xf80a7327ced2d6aba7246e0de1383ddb57fd4475": [],
  "0xfdd33b8413a69ba9ce140b479f27ee7ab133850e": []
}